Workbook

Sheet 說明
A1: 台灣小公司 Excel 記帳系統
A3: 使用說明
A4: 1. 在「日記簿」頁面輸入所有傳票記錄
A5: 2. 科目表可在「科目表」頁面查看和修改
A6: 3. 「試算表」會自動計算每個科目的借貸合計和餘額
A7: 4. 「資產負債表」和「損益表」會自動根據試算表生成
A8: 5. 「VAT計算」頁面顯示進項稅和銷項稅
A10: 日記簿輸入欄位：
A11: - 傳票號：唯一編號（如 2401001）
A12: - 日期：YYYY/MM/DD 格式
A13: - 摘要：交易說明
A14: - 科目代號：必須是科目表中的代號
... A18: 提醒：借方 = 貸方（雙重記帳原則）

Sheet 科目表
A1: 科目代號 | B1: 科目名稱 | C1: 借/貸 | D1: 科目類別
A2: 1111 | B2: 零用金 | C2: 借 | D2: 資產
A3: 1112 | B3: 銀行存款 | C3: 借 | D3: 資產
A4: 11121 | B4: 銀行存款-國泰 | C4: 借 | D4: 資產
A5: 11122 | B5: 銀行存款-合庫 | C5: 借 | D5: 資產
A6: 11123 | B6: 銀行存款-台銀活存 | C6: 借 | D6: 資產
A7: 11124 | B7: 銀行存款-台銀支存 | C7: 借 | D7: 資產
A8: 1113 | B8: 約當現金 | C8: 借 | D8: 資產
A9: 1114 | B9: 短期投資 | C9: 借 | D9: 資產
A10: 1151 | B10: 透過損益按公允價值衡量之金融資產-流動 | C10: 借 | D10: 資產
A11: 1154 | B11: 避險之金融資產-流動 | C11: 借 | D11: 資產
A12: 1158 | B12: 透過其他綜合損益按公允價值衡量之金融資產-流動 | C12: 借 | D12: 資產
... A225: 9500 | B225: 本期其他綜合損益(稅後淨額) | C225: 借 | D225: 所得稅

Sheet 日記簿
A1: 傳票號 | B1: 日期 | C1: 摘要 | D1: 科目代號 | E1: 科目名稱 | F1: 借方金額 | G1: 貸方金額
A2: 2401001 | B2: 2025/01/01 | C2: 公司創立 | D2: 11121 | E2: =IFERROR(VLOOKUP(D2,科目表!$A:$B,2,FALSE),"") | F2: 1000000
A3: 2401001 | B3: 2025/01/01 | C3: 公司創立 | D3: 3110 | E3: =IFERROR(VLOOKUP(D3,科目表!$A:$B,2,FALSE),"") | G3: 1000000
E4: =IFERROR(VLOOKUP(D4,科目表!$A:$B,2,FALSE),"")
E5: =IFERROR(VLOOKUP(D5,科目表!$A:$B,2,FALSE),"")
E6: =IFERROR(VLOOKUP(D6,科目表!$A:$B,2,FALSE),"")
E7: =IFERROR(VLOOKUP(D7,科目表!$A:$B,2,FALSE),"")
E8: =IFERROR(VLOOKUP(D8,科目表!$A:$B,2,FALSE),"")
E9: =IFERROR(VLOOKUP(D9,科目表!$A:$B,2,FALSE),"")
E10: =IFERROR(VLOOKUP(D10,科目表!$A:$B,2,FALSE),"")
E11: =IFERROR(VLOOKUP(D11,科目表!$A:$B,2,FALSE),"")
E12: =IFERROR(VLOOKUP(D12,科目表!$A:$B,2,FALSE),"")
E13: =IFERROR(VLOOKUP(D13,科目表!$A:$B,2,FALSE),"")
E14: =IFERROR(VLOOKUP(D14,科目表!$A:$B,2,FALSE),"")
E15: =IFERROR(VLOOKUP(D15,科目表!$A:$B,2,FALSE),"")
... E99: =IFERROR(VLOOKUP(D99,科目表!$A:$B,2,FALSE),"")

Sheet 試算表
A1: 科目代號 | B1: 科目名稱 | C1: 借方合計 | D1: 貸方合計 | E1: 餘額 | F1: 科目類別
A2: 1111 | B2: 零用金 | C2: =SUMIFS(日記簿!$F$2:$F$100,日記簿!$D$2:$D$100,A2) | D2: =SUMIFS(日記簿!$G$2:$G$100,日記簿!$D$2:$D$100,A2) | E2: =C2-D2 | F2: 資產
A3: 1112 | B3: 銀行存款 | C3: =SUMIFS(日記簿!$F$2:$F$100,日記簿!$D$2:$D$100,A3) | D3: =SUMIFS(日記簿!$G$2:$G$100,日記簿!$D$2:$D$100,A3) | E3: =C3-D3 | F3: 資產
A4: 11121 | B4: 銀行存款-國泰 | C4: =SUMIFS(日記簿!$F$2:$F$100,日記簿!$D$2:$D$100,A4) | D4: =SUMIFS(日記簿!$G$2:$G$100,日記簿!$D$2:$D$100,A4) | E4: =C4-D4 | F4: 資產
A5: 11122 | B5: 銀行存款-合庫 | C5: =SUMIFS(日記簿!$F$2:$F$100,日記簿!$D$2:$D$100,A5) | D5: =SUMIFS(日記簿!$G$2:$G$100,日記簿!$D$2:$D$100,A5) | E5: =C5-D5 | F5: 資產
A6: 11123 | B6: 銀行存款-台銀活存 | C6: =SUMIFS(日記簿!$F$2:$F$100,日記簿!$D$2:$D$100,A6) | D6: =SUMIFS(日記簿!$G$2:$G$100,日記簿!$D$2:$D$100,A6) | E6: =C6-D6 | F6: 資產
A7: 11124 | B7: 銀行存款-台銀支存 | C7: =SUMIFS(日記簿!$F$2:$F$100,日記簿!$D$2:$D$100,A7) | D7: =SUMIFS(日記簿!$G$2:$G$100,日記簿!$D$2:$D$100,A7) | E7: =C7-D7 | F7: 資產
A8: 1113 | B8: 約當現金 | C8: =SUMIFS(日記簿!$F$2:$F$100,日記簿!$D$2:$D$100,A8) | D8: =SUMIFS(日記簿!$G$2:$G$100,日記簿!$D$2:$D$100,A8) | E8: =C8-D8 | F8: 資產
A9: 1114 | B9: 短期投資 | C9: =SUMIFS(日記簿!$F$2:$F$100,日記簿!$D$2:$D$100,A9) | D9: =SUMIFS(日記簿!$G$2:$G$100,日記簿!$D$2:$D$100,A9) | E9: =C9-D9 | F9: 資產
A10: 1151 | B10: 透過損益按公允價值衡量之金融資產-流動 | C10: =SUMIFS(日記簿!$F$2:$F$100,日記簿!$D$2:$D$100,A10) | D10: =SUMIFS(日記簿!$G$2:$G$100,日記簿!$D$2:$D$100,A10) | E10: =C10-D10 | F10: 資產
A11: 1154 | B11: 避險之金融資產-流動 | C11: =SUMIFS(日記簿!$F$2:$F$100,日記簿!$D$2:$D$100,A11) | D11: =SUMIFS(日記簿!$G$2:$G$100,日記簿!$D$2:$D$100,A11) | E11: =C11-D11 | F11: 資產
A12: 1158 | B12: 透過其他綜合損益按公允價值衡量之金融資產-流動 | C12: =SUMIFS(日記簿!$F$2:$F$100,日記簿!$D$2:$D$100,A12) | D12: =SUMIFS(日記簿!$G$2:$G$100,日記簿!$D$2:$D$100,A12) | E12: =C12-D12 | F12: 資產
A13: 1161 | B13: 按攤銷後成本衡量之金融資產－流動 | C13: =SUMIFS(日記簿!$F$2:$F$100,日記簿!$D$2:$D$100,A13) | D13: =SUMIFS(日記簿!$G$2:$G$100,日記簿!$D$2:$D$100,A13) | E13: =C13-D13 | F13: 資產
A14: 1157 | B14: 其他金融資產-流動 | C14: =SUMIFS(日記簿!$F$2:$F$100,日記簿!$D$2:$D$100,A14) | D14: =SUMIFS(日記簿!$G$2:$G$100,日記簿!$D$2:$D$100,A14) | E14: =C14-D14 | F14: 資產
A15: 1159 | B15: 減:累計減損-金融資產-流動 | C15: =SUMIFS(日記簿!$F$2:$F$100,日記簿!$D$2:$D$100,A15) | D15: =SUMIFS(日記簿!$G$2:$G$100,日記簿!$D$2:$D$100,A15) | E15: =D15-C15 | F15: 資產
A16: 1125 | B16: 合約資產-流動 | C16: =SUMIFS(日記簿!$F$2:$F$100,日記簿!$D$2:$D$100,A16) | D16: =SUMIFS(日記簿!$G$2:$G$100,日記簿!$D$2:$D$100,A16) | E16: =C16-D16 | F16: 資產
A17: 1126 | B17: 減:累計減損-合約資產-流動 | C17: =SUMIFS(日記簿!$F$2:$F$100,日記簿!$D$2:$D$100,A17) | D17: =SUMIFS(日記簿!$G$2:$G$100,日記簿!$D$2:$D$100,A17) | E17: =D17-C17 | F17: 資產
A18: 1121 | B18: 應收票據 | C18: =SUMIFS(日記簿!$F$2:$F$100,日記簿!$D$2:$D$100,A18) | D18: =SUMIFS(日記簿!$G$2:$G$100,日記簿!$D$2:$D$100,A18) | E18: =C18-D18 | F18: 資產
A19: 1122 | B19: 減:備抵呆帳-應收票據 | C19: =SUMIFS(日記簿!$F$2:$F$100,日記簿!$D$2:$D$100,A19) | D19: =SUMIFS(日記簿!$G$2:$G$100,日記簿!$D$2:$D$100,A19) | E19: =D19-C19 | F19: 資產
A20: 1123 | B20: 應收帳款 | C20: =SUMIFS(日記簿!$F$2:$F$100,日記簿!$D$2:$D$100,A20) | D20: =SUMIFS(日記簿!$G$2:$G$100,日記簿!$D$2:$D$100,A20) | E20: =C20-D20 | F20: 資產
A21: 1124 | B21: 減:備抵呆帳-應收帳款 | C21: =SUMIFS(日記簿!$F$2:$F$100,日記簿!$D$2:$D$100,A21) | D21: =SUMIFS(日記簿!$G$2:$G$100,日記簿!$D$2:$D$100,A21) | E21: =D21-C21 | F21: 資產
A22: 1129 | B22: 其他應收款 | C22: =SUMIFS(日記簿!$F$2:$F$100,日記簿!$D$2:$D$100,A22) | D22: =SUMIFS(日記簿!$G$2:$G$100,日記簿!$D$2:$D$100,A22) | E22: =C22-D22 | F22: 資產
A23: 1131 | B23: 商品 | C23: =SUMIFS(日記簿!$F$2:$F$100,日記簿!$D$2:$D$100,A23) | D23: =SUMIFS(日記簿!$G$2:$G$100,日記簿!$D$2:$D$100,A23) | E23: =C23-D23 | F23: 資產
A24: 1132 | B24: 製成品 | C24: =SUMIFS(日記簿!$F$2:$F$100,日記簿!$D$2:$D$100,A24) | D24: =SUMIFS(日記簿!$G$2:$G$100,日記簿!$D$2:$D$100,A24) | E24: =C24-D24 | F24: 資產
A25: 1133 | B25: 在製品 | C25: =SUMIFS(日記簿!$F$2:$F$100,日記簿!$D$2:$D$100,A25) | D25: =SUMIFS(日記簿!$G$2:$G$100,日記簿!$D$2:$D$100,A25) | E25: =C25-D25 | F25: 資產
A26: 1134 | B26: 原料 | C26: =SUMIFS(日記簿!$F$2:$F$100,日記簿!$D$2:$D$100,A26) | D26: =SUMIFS(日記簿!$G$2:$G$100,日記簿!$D$2:$D$100,A26) | E26: =C26-D26 | F26: 資產
A27: 1135 | B27: 物料 | C27: =SUMIFS(日記簿!$F$2:$F$100,日記簿!$D$2:$D$100,A27) | D27: =SUMIFS(日記簿!$G$2:$G$100,日記簿!$D$2:$D$100,A27) | E27: =C27-D27 | F27: 資產
A28: 1136 | B28: 寄銷品 | C28: =SUMIFS(日記簿!$F$2:$F$100,日記簿!$D$2:$D$100,A28) | D28: =SUMIFS(日記簿!$G$2:$G$100,日記簿!$D$2:$D$100,A28) | E28: =C28-D28 | F28: 資產
A29: 1138 | B29: 其他存貨 | C29: =SUMIFS(日記簿!$F$2:$F$100,日記簿!$D$2:$D$100,A29) | D29: =SUMIFS(日記簿!$G$2:$G$100,日記簿!$D$2:$D$100,A29) | E29: =C29-D29 | F29: 資產
A30: 1137 | B30: 備抵存貨跌價損失 | C30: =SUMIFS(日記簿!$F$2:$F$100,日記簿!$D$2:$D$100,A30) | D30: =SUMIFS(日記簿!$G$2:$G$100,日記簿!$D$2:$D$100,A30) | E30: =D30-C30 | F30: 資產
A31: 1141 | B31: 預付費用 | C31: =SUMIFS(日記簿!$F$2:$F$100,日記簿!$D$2:$D$100,A31) | D31: =SUMIFS(日記簿!$G$2:$G$100,日記簿!$D$2:$D$100,A31) | E31: =C31-D31 | F31: 資產
A32: 1142 | B32: 用品盤存 | C32: =SUMIFS(日記簿!$F$2:$F$100,日記簿!$D$2:$D$100,A32) | D32: =SUMIFS(日記簿!$G$2:$G$100,日記簿!$D$2:$D$100,A32) | E32: =C32-D32 | F32: 資產
A33: 1143 | B33: 預付貨款 | C33: =SUMIFS(日記簿!$F$2:$F$100,日記簿!$D$2:$D$100,A33) | D33: =SUMIFS(日記簿!$G$2:$G$100,日記簿!$D$2:$D$100,A33) | E33: =C33-D33 | F33: 資產
A34: 1144 | B34: 進項稅額 | C34: =SUMIFS(日記簿!$F$2:$F$100,日記簿!$D$2:$D$100,A34) | D34: =SUMIFS(日記簿!$G$2:$G$100,日記簿!$D$2:$D$100,A34) | E34: =C34-D34 | F34: 資產
A35: 1145 | B35: 留抵稅額 | C35: =SUMIFS(日記簿!$F$2:$F$100,日記簿!$D$2:$D$100,A35) | D35: =SUMIFS(日記簿!$G$2:$G$100,日記簿!$D$2:$D$100,A35) | E35: =C35-D35 | F35: 資產
A36: 1149 | B36: 其他預付款 | C36: =SUMIFS(日記簿!$F$2:$F$100,日記簿!$D$2:$D$100,A36) | D36: =SUMIFS(日記簿!$G$2:$G$100,日記簿!$D$2:$D$100,A36) | E36: =C36-D36 | F36: 資產
A37: 1191 | B37: 暫付款 | C37: =SUMIFS(日記簿!$F$2:$F$100,日記簿!$D$2:$D$100,A37) | D37: =SUMIFS(日記簿!$G$2:$G$100,日記簿!$D$2:$D$100,A37) | E37: =C37-D37 | F37: 資產
A38: 1192 | B38: 股東往來 | C38: =SUMIFS(日記簿!$F$2:$F$100,日記簿!$D$2:$D$100,A38) | D38: =SUMIFS(日記簿!$G$2:$G$100,日記簿!$D$2:$D$100,A38) | E38: =C38-D38 | F38: 資產
A39: 1193 | B39: 同業往來 | C39: =SUMIFS(日記簿!$F$2:$F$100,日記簿!$D$2:$D$100,A39) | D39: =SUMIFS(日記簿!$G$2:$G$100,日記簿!$D$2:$D$100,A39) | E39: =C39-D39 | F39: 資產
A40: 1199 | B40: 其他流動資產-其他 | C40: =SUMIFS(日記簿!$F$2:$F$100,日記簿!$D$2:$D$100,A40) | D40: =SUMIFS(日記簿!$G$2:$G$100,日記簿!$D$2:$D$100,A40) | E40: =C40-D40 | F40: 資產
A41: 1300 | B41: 長期性之投資 | C41: =SUMIFS(日記簿!$F$2:$F$100,日記簿!$D$2:$D$100,A41) | D41: =SUMIFS(日記簿!$G$2:$G$100,日記簿!$D$2:$D$100,A41) | E41: =C41-D41 | F41: 資產
A42: 1415 | B42: 減:累計減損-長期性之投資 | C42: =SUMIFS(日記簿!$F$2:$F$100,日記簿!$D$2:$D$100,A42) | D42: =SUMIFS(日記簿!$G$2:$G$100,日記簿!$D$2:$D$100,A42) | E42: =D42-C42 | F42: 資產
A43: 1612 | B43: 透過損益按公允價值衡量之金融資產-非流動 | C43: =SUMIFS(日記簿!$F$2:$F$100,日記簿!$D$2:$D$100,A43) | D43: =SUMIFS(日記簿!$G$2:$G$100,日記簿!$D$2:$D$100,A43) | E43: =C43-D43 | F43: 資產
A44: 1615 | B44: 避險之金融資產-非流動 | C44: =SUMIFS(日記簿!$F$2:$F$100,日記簿!$D$2:$D$100,A44) | D44: =SUMIFS(日記簿!$G$2:$G$100,日記簿!$D$2:$D$100,A44) | E44: =C44-D44 | F44: 資產
A45: 1621 | B45: 透過其他綜合損益按公允價值衡量之金融資產-非流動 | C45: =SUMIFS(日記簿!$F$2:$F$100,日記簿!$D$2:$D$100,A45) | D45: =SUMIFS(日記簿!$G$2:$G$100,日記簿!$D$2:$D$100,A45) | E45: =C45-D45 | F45: 資產
A46: 1622 | B46: 按攤銷後成本衡量之金融資產－非流動 | C46: =SUMIFS(日記簿!$F$2:$F$100,日記簿!$D$2:$D$100,A46) | D46: =SUMIFS(日記簿!$G$2:$G$100,日記簿!$D$2:$D$100,A46) | E46: =C46-D46 | F46: 資產
A47: 1618 | B47: 其他金融資產-非流動 | C47: =SUMIFS(日記簿!$F$2:$F$100,日記簿!$D$2:$D$100,A47) | D47: =SUMIFS(日記簿!$G$2:$G$100,日記簿!$D$2:$D$100,A47) | E47: =C47-D47 | F47: 資產
A48: 1630 | B48: 採用權益法之投資 | C48: =SUMIFS(日記簿!$F$2:$F$100,日記簿!$D$2:$D$100,A48) | D48: =SUMIFS(日記簿!$G$2:$G$100,日記簿!$D$2:$D$100,A48) | E48: =C48-D48 | F48: 資產
A49: 1631 | B49: 減:累計減損-金融資產-非流動 | C49: =SUMIFS(日記簿!$F$2:$F$100,日記簿!$D$2:$D$100,A49) | D49: =SUMIFS(日記簿!$G$2:$G$100,日記簿!$D$2:$D$100,A49) | E49: =D49-C49 | F49: 資產
A50: 1640 | B50: 合約資產-非流動 | C50: =SUMIFS(日記簿!$F$2:$F$100,日記簿!$D$2:$D$100,A50) | D50: =SUMIFS(日記簿!$G$2:$G$100,日記簿!$D$2:$D$100,A50) | E50: =C50-D50 | F50: 資產
A51: 1641 | B51: 減:累計減損-合約資產-非流動 | C51: =SUMIFS(日記簿!$F$2:$F$100,日記簿!$D$2:$D$100,A51) | D51: =SUMIFS(日記簿!$G$2:$G$100,日記簿!$D$2:$D$100,A51) | E51: =D51-C51 | F51: 資產
A52: 1410 | B52: 土地 | C52: =SUMIFS(日記簿!$F$2:$F$100,日記簿!$D$2:$D$100,A52) | D52: =SUMIFS(日記簿!$G$2:$G$100,日記簿!$D$2:$D$100,A52) | E52: =C52-D52 | F52: 資產
A53: 1411 | B53: 減:累計減損-土地 | C53: =SUMIFS(日記簿!$F$2:$F$100,日記簿!$D$2:$D$100,A53) | D53: =SUMIFS(日記簿!$G$2:$G$100,日記簿!$D$2:$D$100,A53) | E53: =D53-C53 | F53: 資產
A54: 1431 | B54: 房屋及建築 | C54: =SUMIFS(日記簿!$F$2:$F$100,日記簿!$D$2:$D$100,A54) | D54: =SUMIFS(日記簿!$G$2:$G$100,日記簿!$D$2:$D$100,A54) | E54: =C54-D54 | F54: 資產
A55: 1432 | B55: 減:累計折舊-房屋及建築 | C55: =SUMIFS(日記簿!$F$2:$F$100,日記簿!$D$2:$D$100,A55) | D55: =SUMIFS(日記簿!$G$2:$G$100,日記簿!$D$2:$D$100,A55) | E55: =D55-C55 | F55: 資產
A56: 1433 | B56: 減:累計減損-房屋及建築 | C56: =SUMIFS(日記簿!$F$2:$F$100,日記簿!$D$2:$D$100,A56) | D56: =SUMIFS(日記簿!$G$2:$G$100,日記簿!$D$2:$D$100,A56) | E56: =D56-C56 | F56: 資產
A57: 1441 | B57: 機器設備 | C57: =SUMIFS(日記簿!$F$2:$F$100,日記簿!$D$2:$D$100,A57) | D57: =SUMIFS(日記簿!$G$2:$G$100,日記簿!$D$2:$D$100,A57) | E57: =C57-D57 | F57: 資產
A58: 1442 | B58: 減:累計折舊-機器設備 | C58: =SUMIFS(日記簿!$F$2:$F$100,日記簿!$D$2:$D$100,A58) | D58: =SUMIFS(日記簿!$G$2:$G$100,日記簿!$D$2:$D$100,A58) | E58: =D58-C58 | F58: 資產
A59: 1443 | B59: 減:累計減損-機器設備 | C59: =SUMIFS(日記簿!$F$2:$F$100,日記簿!$D$2:$D$100,A59) | D59: =SUMIFS(日記簿!$G$2:$G$100,日記簿!$D$2:$D$100,A59) | E59: =D59-C59 | F59: 資產
A60: 1451 | B60: 運輸設備 | C60: =SUMIFS(日記簿!$F$2:$F$100,日記簿!$D$2:$D$100,A60) | D60: =SUMIFS(日記簿!$G$2:$G$100,日記簿!$D$2:$D$100,A60) | E60: =C60-D60 | F60: 資產
A61: 1452 | B61: 減:累計折舊-運輸設備 | C61: =SUMIFS(日記簿!$F$2:$F$100,日記簿!$D$2:$D$100,A61) | D61: =SUMIFS(日記簿!$G$2:$G$100,日記簿!$D$2:$D$100,A61) | E61: =D61-C61 | F61: 資產
A62: 1453 | B62: 減:累計減損-運輸設備 | C62: =SUMIFS(日記簿!$F$2:$F$100,日記簿!$D$2:$D$100,A62) | D62: =SUMIFS(日記簿!$G$2:$G$100,日記簿!$D$2:$D$100,A62) | E62: =D62-C62 | F62: 資產
A63: 1461 | B63: 生財器具 | C63: =SUMIFS(日記簿!$F$2:$F$100,日記簿!$D$2:$D$100,A63) | D63: =SUMIFS(日記簿!$G$2:$G$100,日記簿!$D$2:$D$100,A63) | E63: =C63-D63 | F63: 資產
A64: 1462 | B64: 減:累計折舊-生財器具 | C64: =SUMIFS(日記簿!$F$2:$F$100,日記簿!$D$2:$D$100,A64) | D64: =SUMIFS(日記簿!$G$2:$G$100,日記簿!$D$2:$D$100,A64) | E64: =D64-C64 | F64: 資產
A65: 1463 | B65: 減:累計減損-生財器具 | C65: =SUMIFS(日記簿!$F$2:$F$100,日記簿!$D$2:$D$100,A65) | D65: =SUMIFS(日記簿!$G$2:$G$100,日記簿!$D$2:$D$100,A65) | E65: =D65-C65 | F65: 資產
A66: 1470 | B66: 未完工程及待驗設備 | C66: =SUMIFS(日記簿!$F$2:$F$100,日記簿!$D$2:$D$100,A66) | D66: =SUMIFS(日記簿!$G$2:$G$100,日記簿!$D$2:$D$100,A66) | E66: =C66-D66 | F66: 資產
A67: 1580 | B67: 預付購置設備款 | C67: =SUMIFS(日記簿!$F$2:$F$100,日記簿!$D$2:$D$100,A67) | D67: =SUMIFS(日記簿!$G$2:$G$100,日記簿!$D$2:$D$100,A67) | E67: =C67-D67 | F67: 資產
A68: 1491 | B68: 其他固定資產 | C68: =SUMIFS(日記簿!$F$2:$F$100,日記簿!$D$2:$D$100,A68) | D68: =SUMIFS(日記簿!$G$2:$G$100,日記簿!$D$2:$D$100,A68) | E68: =C68-D68 | F68: 資產
A69: 1492 | B69: 減:累計折舊-其他固定資產 | C69: =SUMIFS(日記簿!$F$2:$F$100,日記簿!$D$2:$D$100,A69) | D69: =SUMIFS(日記簿!$G$2:$G$100,日記簿!$D$2:$D$100,A69) | E69: =D69-C69 | F69: 資產
A70: 1493 | B70: 減:累計減損-其他固定資產 | C70: =SUMIFS(日記簿!$F$2:$F$100,日記簿!$D$2:$D$100,A70) | D70: =SUMIFS(日記簿!$G$2:$G$100,日記簿!$D$2:$D$100,A70) | E70: =D70-C70 | F70: 資產
A71: 1541 | B71: 投資性不動產 | C71: =SUMIFS(日記簿!$F$2:$F$100,日記簿!$D$2:$D$100,A71) | D71: =SUMIFS(日記簿!$G$2:$G$100,日記簿!$D$2:$D$100,A71) | E71: =C71-D71 | F71: 資產
A72: 1542 | B72: 減:累計折舊-投資性不動產 | C72: =SUMIFS(日記簿!$F$2:$F$100,日記簿!$D$2:$D$100,A72) | D72: =SUMIFS(日記簿!$G$2:$G$100,日記簿!$D$2:$D$100,A72) | E72: =D72-C72 | F72: 資產
A73: 1421 | B73: 礦產資源 | C73: =SUMIFS(日記簿!$F$2:$F$100,日記簿!$D$2:$D$100,A73) | D73: =SUMIFS(日記簿!$G$2:$G$100,日記簿!$D$2:$D$100,A73) | E73: =C73-D73 | F73: 資產
A74: 1422 | B74: 減:累計折耗-礦產資源 | C74: =SUMIFS(日記簿!$F$2:$F$100,日記簿!$D$2:$D$100,A74) | D74: =SUMIFS(日記簿!$G$2:$G$100,日記簿!$D$2:$D$100,A74) | E74: =D74-C74 | F74: 資產
A75: 1551 | B75: 生物資產 | C75: =SUMIFS(日記簿!$F$2:$F$100,日記簿!$D$2:$D$100,A75) | D75: =SUMIFS(日記簿!$G$2:$G$100,日記簿!$D$2:$D$100,A75) | E75: =C75-D75 | F75: 資產
A76: 1552 | B76: 減:累計折舊-生物資產 | C76: =SUMIFS(日記簿!$F$2:$F$100,日記簿!$D$2:$D$100,A76) | D76: =SUMIFS(日記簿!$G$2:$G$100,日記簿!$D$2:$D$100,A76) | E76: =D76-C76 | F76: 資產
A77: 1553 | B77: 減:累計減損-生物資產 | C77: =SUMIFS(日記簿!$F$2:$F$100,日記簿!$D$2:$D$100,A77) | D77: =SUMIFS(日記簿!$G$2:$G$100,日記簿!$D$2:$D$100,A77) | E77: =D77-C77 | F77: 資產
A78: 1510 | B78: 無形資產 | C78: =SUMIFS(日記簿!$F$2:$F$100,日記簿!$D$2:$D$100,A78) | D78: =SUMIFS(日記簿!$G$2:$G$100,日記簿!$D$2:$D$100,A78) | E78: =C78-D78 | F78: 資產
A79: 1511 | B79: 減:累計攤折-無形資產 | C79: =SUMIFS(日記簿!$F$2:$F$100,日記簿!$D$2:$D$100,A79) | D79: =SUMIFS(日記簿!$G$2:$G$100,日記簿!$D$2:$D$100,A79) | E79: =D79-C79 | F79: 資產
A80: 1512 | B80: 減:累計減損-無形資產 | C80: =SUMIFS(日記簿!$F$2:$F$100,日記簿!$D$2:$D$100,A80) | D80: =SUMIFS(日記簿!$G$2:$G$100,日記簿!$D$2:$D$100,A80) | E80: =D80-C80 | F80: 資產
A81: 1901 | B81: 存出保證金 | C81: =SUMIFS(日記簿!$F$2:$F$100,日記簿!$D$2:$D$100,A81) | D81: =SUMIFS(日記簿!$G$2:$G$100,日記簿!$D$2:$D$100,A81) | E81: =C81-D81 | F81: 資產
A82: 1902 | B82: 未攤銷費用 | C82: =SUMIFS(日記簿!$F$2:$F$100,日記簿!$D$2:$D$100,A82) | D82: =SUMIFS(日記簿!$G$2:$G$100,日記簿!$D$2:$D$100,A82) | E82: =C82-D82 | F82: 資產
A83: 1903 | B83: 預付設備款 | C83: =SUMIFS(日記簿!$F$2:$F$100,日記簿!$D$2:$D$100,A83) | D83: =SUMIFS(日記簿!$G$2:$G$100,日記簿!$D$2:$D$100,A83) | E83: =C83-D83 | F83: 資產
A84: 1904 | B84: 其他非流動資產-其他 | C84: =SUMIFS(日記簿!$F$2:$F$100,日記簿!$D$2:$D$100,A84) | D84: =SUMIFS(日記簿!$G$2:$G$100,日記簿!$D$2:$D$100,A84) | E84: =C84-D84 | F84: 資產
A85: 2111 | B85: 銀行透支 | C85: =SUMIFS(日記簿!$F$2:$F$100,日記簿!$D$2:$D$100,A85) | D85: =SUMIFS(日記簿!$G$2:$G$100,日記簿!$D$2:$D$100,A85) | E85: =D85-C85 | F85: 負債
A86: 2112 | B86: 銀行借款 | C86: =SUMIFS(日記簿!$F$2:$F$100,日記簿!$D$2:$D$100,A86) | D86: =SUMIFS(日記簿!$G$2:$G$100,日記簿!$D$2:$D$100,A86) | E86: =D86-C86 | F86: 負債
A87: 2113 | B87: 應付短期票券 | C87: =SUMIFS(日記簿!$F$2:$F$100,日記簿!$D$2:$D$100,A87) | D87: =SUMIFS(日記簿!$G$2:$G$100,日記簿!$D$2:$D$100,A87) | E87: =D87-C87 | F87: 負債
A88: 2119 | B88: 其他短期借款 | C88: =SUMIFS(日記簿!$F$2:$F$100,日記簿!$D$2:$D$100,A88) | D88: =SUMIFS(日記簿!$G$2:$G$100,日記簿!$D$2:$D$100,A88) | E88: =D88-C88 | F88: 負債
A89: 2140 | B89: 透過損益按公允價值衡量之金融負債-流動 | C89: =SUMIFS(日記簿!$F$2:$F$100,日記簿!$D$2:$D$100,A89) | D89: =SUMIFS(日記簿!$G$2:$G$100,日記簿!$D$2:$D$100,A89) | E89: =D89-C89 | F89: 負債
A90: 2150 | B90: 避險之金融負債-流動 | C90: =SUMIFS(日記簿!$F$2:$F$100,日記簿!$D$2:$D$100,A90) | D90: =SUMIFS(日記簿!$G$2:$G$100,日記簿!$D$2:$D$100,A90) | E90: =D90-C90 | F90: 負債
A91: 2170 | B91: 特別股負債-流動 | C91: =SUMIFS(日記簿!$F$2:$F$100,日記簿!$D$2:$D$100,A91) | D91: =SUMIFS(日記簿!$G$2:$G$100,日記簿!$D$2:$D$100,A91) | E91: =D91-C91 | F91: 負債
A92: 2180 | B92: 其他金融負債-流動 | C92: =SUMIFS(日記簿!$F$2:$F$100,日記簿!$D$2:$D$100,A92) | D92: =SUMIFS(日記簿!$G$2:$G$100,日記簿!$D$2:$D$100,A92) | E92: =D92-C92 | F92: 負債
A93: 2126 | B93: 合約負債-流動 | C93: =SUMIFS(日記簿!$F$2:$F$100,日記簿!$D$2:$D$100,A93) | D93: =SUMIFS(日記簿!$G$2:$G$100,日記簿!$D$2:$D$100,A93) | E93: =D93-C93 | F93: 負債
A94: 2120 | B94: 應付票據 | C94: =SUMIFS(日記簿!$F$2:$F$100,日記簿!$D$2:$D$100,A94) | D94: =SUMIFS(日記簿!$G$2:$G$100,日記簿!$D$2:$D$100,A94) | E94: =D94-C94 | F94: 負債
A95: 2121 | B95: 應付帳款 | C95: =SUMIFS(日記簿!$F$2:$F$100,日記簿!$D$2:$D$100,A95) | D95: =SUMIFS(日記簿!$G$2:$G$100,日記簿!$D$2:$D$100,A95) | E95: =D95-C95 | F95: 負債
A96: 2131 | B96: 應付費用 | C96: =SUMIFS(日記簿!$F$2:$F$100,日記簿!$D$2:$D$100,A96) | D96: =SUMIFS(日記簿!$G$2:$G$100,日記簿!$D$2:$D$100,A96) | E96: =D96-C96 | F96: 負債
... A137: 3506 | B137: 其他權益-其他 | C137: =SUMIFS(日記簿!$F$2:$F$100,日記簿!$D$2:$D$100,A137) | D137: =SUMIFS(日記簿!$G$2:$G$100,日記簿!$D$2:$D$100,A137) | E137: =D137-C137 | F137: 權益
A138: 3600 | B138: 減:庫藏股票 | C138: =SUMIFS(日記簿!$F$2:$F$100,日記簿!$D$2:$D$100,A138) | D138: =SUMIFS(日記簿!$G$2:$G$100,日記簿!$D$2:$D$100,A138) | E138: =C138-D138 | F138: 權益
A139: 4100 | B139: 銷貨收入 | C139: =SUMIFS(日記簿!$F$2:$F$100,日記簿!$D$2:$D$100,A139) | D139: =SUMIFS(日記簿!$G$2:$G$100,日記簿!$D$2:$D$100,A139) | E139: =D139-C139 | F139: 收入
A140: 4110 | B140: 減:銷貨退回 | C140: =SUMIFS(日記簿!$F$2:$F$100,日記簿!$D$2:$D$100,A140) | D140: =SUMIFS(日記簿!$G$2:$G$100,日記簿!$D$2:$D$100,A140) | E140: =C140-D140 | F140: 收入
...

Sheet 資產負債表
A1: 資產負債表
A2: 截至 2026年04月28日
A4: 資產 | D4: 負債及權益
A5: 流動資產 | B5: =SUMIF(試算表!$F$2:$F$225,"資產",試算表!$E$2:$E$225) | D5: 流動負債 | E5: =SUMIF(試算表!$F$2:$F$225,"負債",試算表!$E$2:$E$225)
A6: 非流動資產 | B6: 0 | D6: 非流動負債 | E6: 0
A7: 資產總計 | B7: =B5+B6 | D7: 股東權益 | E7: =SUMIF(試算表!$F$2:$F$225,"權益",試算表!$E$2:$E$225)
D8: 負債及權益總計 | E8: =E5+E6+E7

Sheet 損益表
A1: 損益表
A2: 自 2026年04月 起
A4: 營業收入 | B4: =SUMIF(試算表!$F$2:$F$225,"收入",試算表!$E$2:$E$225)
A5: 4100 銷貨收入 | B5: =VLOOKUP(4100,試算表!$A:$E,5,FALSE)
A6: 4110 減:銷貨退回 | B6: =VLOOKUP(4110,試算表!$A:$E,5,FALSE)
A7: 4120 減:銷貨折讓 | B7: =VLOOKUP(4120,試算表!$A:$E,5,FALSE)
A8: 4200 勞務收入 | B8: =VLOOKUP(4200,試算表!$A:$E,5,FALSE)
A9: 4300 加工收入 | B9: =VLOOKUP(4300,試算表!$A:$E,5,FALSE)
A10: 4400 工程收入 | B10: =VLOOKUP(4400,試算表!$A:$E,5,FALSE)
A12: 銷貨成本 | B12: =SUMIF(試算表!$F$2:$F$225,"銷貨成本",試算表!$E$2:$E$225)
A13: 5100 銷貨成本 | B13: =VLOOKUP(5100,試算表!$A:$E,5,FALSE)
A14: 5200 勞務成本 | B14: =VLOOKUP(5200,試算表!$A:$E,5,FALSE)
A15: 5300 加工成本 | B15: =VLOOKUP(5300,試算表!$A:$E,5,FALSE)
A16: 5400 工程成本 | B16: =VLOOKUP(5400,試算表!$A:$E,5,FALSE)
A18: 營業毛利 | B18: =B4-B12
A20: 營業費用 | B20: =SUMIF(試算表!$F$2:$F$225,"費用",試算表!$E$2:$E$225)
A21: 6010 薪資支出 | B21: =VLOOKUP(6010,試算表!$A:$E,5,FALSE)
A22: 6020 租金支出 | B22: =VLOOKUP(6020,試算表!$A:$E,5,FALSE)
A23: 6030 文具用品 | B23: =VLOOKUP(6030,試算表!$A:$E,5,FALSE)
A24: 6040 旅費 | B24: =VLOOKUP(6040,試算表!$A:$E,5,FALSE)
A25: 6050 運費 | B25: =VLOOKUP(6050,試算表!$A:$E,5,FALSE)
A26: 6060 郵電費 | B26: =VLOOKUP(6060,試算表!$A:$E,5,FALSE)
A27: 6070 修繕費 | B27: =VLOOKUP(6070,試算表!$A:$E,5,FALSE)
A28: 6080 廣告費 | B28: =VLOOKUP(6080,試算表!$A:$E,5,FALSE)
A29: 6090 水電瓦斯費 | B29: =VLOOKUP(6090,試算表!$A:$E,5,FALSE)
A30: 6100 保險費 | B30: =VLOOKUP(6100,試算表!$A:$E,5,FALSE)
A31: 6110 交際費 | B31: =VLOOKUP(6110,試算表!$A:$E,5,FALSE)
A32: 6120 捐贈 | B32: =VLOOKUP(6120,試算表!$A:$E,5,FALSE)
A33: 6130 稅捐 | B33: =VLOOKUP(6130,試算表!$A:$E,5,FALSE)
A34: 6140 呆帳損失 | B34: =VLOOKUP(6140,試算表!$A:$E,5,FALSE)
A35: 6150 折舊 | B35: =VLOOKUP(6150,試算表!$A:$E,5,FALSE)
A36: 6160 各項耗竭及攤提 | B36: =VLOOKUP(6160,試算表!$A:$E,5,FALSE)
A37: 6170 外銷損失 | B37: =VLOOKUP(6170,試算表!$A:$E,5,FALSE)
A38: 6180 伙食費 | B38: =VLOOKUP(6180,試算表!$A:$E,5,FALSE)
A39: 6190 職工福利 | B39: =VLOOKUP(6190,試算表!$A:$E,5,FALSE)
A40: 6200 研究費 | B40: =VLOOKUP(6200,試算表!$A:$E,5,FALSE)
A41: 6210 佣金支出 | B41: =VLOOKUP(6210,試算表!$A:$E,5,FALSE)
A42: 6220 訓練費 | B42: =VLOOKUP(6220,試算表!$A:$E,5,FALSE)
A43: 6230 其他費用 | B43: =VLOOKUP(6230,試算表!$A:$E,5,FALSE)
A44: 6240 加班費 | B44: =VLOOKUP(6240,試算表!$A:$E,5,FALSE)
A45: 6250 退休金 | B45: =VLOOKUP(6250,試算表!$A:$E,5,FALSE)
A46: 6260 書報雜誌 | B46: =VLOOKUP(6260,試算表!$A:$E,5,FALSE)
A47: 6270 雜項購置 | B47: =VLOOKUP(6270,試算表!$A:$E,5,FALSE)
A48: 6280 出口費用 | B48: =VLOOKUP(6280,試算表!$A:$E,5,FALSE)
A49: 6290 手續費 | B49: =VLOOKUP(6290,試算表!$A:$E,5,FALSE)
A50: 6300 匯費 | B50: =VLOOKUP(6300,試算表!$A:$E,5,FALSE)
A51: 6310 檢驗費 | B51: =VLOOKUP(6310,試算表!$A:$E,5,FALSE)
A52: 6320 交通費 | B52: =VLOOKUP(6320,試算表!$A:$E,5,FALSE)
A53: 6330 公會費 | B53: =VLOOKUP(6330,試算表!$A:$E,5,FALSE)
A54: 6340 燃料費 | B54: =VLOOKUP(6340,試算表!$A:$E,5,FALSE)
A55: 6350 醫藥費 | B55: =VLOOKUP(6350,試算表!$A:$E,5,FALSE)
A56: 6360 規費 | B56: =VLOOKUP(6360,試算表!$A:$E,5,FALSE)
A57: 6370 包裝費 | B57: =VLOOKUP(6370,試算表!$A:$E,5,FALSE)
A58: 6380 加工費用 | B58: =VLOOKUP(6380,試算表!$A:$E,5,FALSE)
A59: 6390 消耗費 | B59: =VLOOKUP(6390,試算表!$A:$E,5,FALSE)
A60: 6400 勞務費 | B60: =VLOOKUP(6400,試算表!$A:$E,5,FALSE)
A61: 6410 倉租 | B61: =VLOOKUP(6410,試算表!$A:$E,5,FALSE)
A62: 6420 報關費 | B62: =VLOOKUP(6420,試算表!$A:$E,5,FALSE)
A63: 6430 進口運費 | B63: =VLOOKUP(6430,試算表!$A:$E,5,FALSE)
A64: 6440 出口結匯費 | B64: =VLOOKUP(6440,試算表!$A:$E,5,FALSE)
A65: 6450 碼頭工資 | B65: =VLOOKUP(6450,試算表!$A:$E,5,FALSE)
A66: 6460 服務費 | B66: =VLOOKUP(6460,試算表!$A:$E,5,FALSE)
A67: 6470 清潔費 | B67: =VLOOKUP(6470,試算表!$A:$E,5,FALSE)
A68: 6480 樣品費 | B68: =VLOOKUP(6480,試算表!$A:$E,5,FALSE)
A69: 6490 稿費 | B69: =VLOOKUP(6490,試算表!$A:$E,5,FALSE)
A70: 6500 排印費 | B70: =VLOOKUP(6500,試算表!$A:$E,5,FALSE)
A71: 6510 製版費 | B71: =VLOOKUP(6510,試算表!$A:$E,5,FALSE)
A72: 6520 出版費 | B72: =VLOOKUP(6520,試算表!$A:$E,5,FALSE)
A73: 6530 工具費 | B73: =VLOOKUP(6530,試算表!$A:$E,5,FALSE)
A75: 營業淨利 | B75: =B18-B20
A77: 稅前損益 | B77: =B75
A78: 所得稅費用 | B78: =SUMIF(試算表!$F$2:$F$225,"所得稅",試算表!$E$2:$E$225)
A79: 9000 所得稅費用(利益) | B79: =VLOOKUP(9000,試算表!$A:$E,5,FALSE)
A80: 9500 本期其他綜合損益(稅後淨額) | B80: =VLOOKUP(9500,試算表!$A:$E,5,FALSE)
A82: 稅後損益 | B82: =B77-B78

Sheet VAT計算
A1: 增值稅（VAT）計算
A2: 台灣營業稅率：5%
A4: 進項稅額（科目 1144） | B4: =VLOOKUP("1144",試算表!$A:$E,5,FALSE)
A6: 銷項稅額（科目 2171） | B6: =VLOOKUP("2171",試算表!$A:$E,5,FALSE)
A8: 應繳增值稅 | B8: =B6-B4
A11: 說明：
A12: 應繳 VAT > 0：需繳稅
A13: 應繳 VAT < 0：可退稅（負數表示待退）
A14: 應繳 VAT = 0：不需繳退
