Workbook

Sheet 說明
A1: 台灣小公司 Excel 記帳系統
A3: 使用說明
A4: 1. 在「日記簿」頁面輸入所有傳票記錄
A5: 2. 科目表可在「科目表」頁面查看和修改
A6: 3. 「試算表」會自動計算每個科目的借貸合計和餘額
A7: 4. 「資產負債表」和「損益表」會自動根據試算表生成
A8: 5. 「VAT計算」頁面顯示進項稅和銷項稅
A10: 日記簿輸入欄位：
A11: - 傳票號：唯一編號（如 2401001）
A12: - 日期：YYYY/MM/DD 格式
A13: - 摘要：交易說明
A14: - 科目代號：必須是科目表中的代號
... A18: 提醒：借方 = 貸方（雙重記帳原則）

Sheet 科目表
A1: 科目代號 | B1: 科目名稱 | C1: 借/貸 | D1: 科目類別 | E1: BS分類
A2: 1111 | B2: 零用金 | C2: 借 | D2: 資產 | E2: 流動資產
A3: 1112 | B3: 銀行存款 | C3: 借 | D3: 資產 | E3: 流動資產
A4: 11121 | B4: 銀行存款-國泰 | C4: 借 | D4: 資產 | E4: 流動資產
A5: 11122 | B5: 銀行存款-合庫 | C5: 借 | D5: 資產 | E5: 流動資產
A6: 11123 | B6: 銀行存款-台銀活存 | C6: 借 | D6: 資產 | E6: 流動資產
A7: 11124 | B7: 銀行存款-台銀支存 | C7: 借 | D7: 資產 | E7: 流動資產
A8: 1113 | B8: 約當現金 | C8: 借 | D8: 資產 | E8: 流動資產
A9: 1114 | B9: 短期投資 | C9: 借 | D9: 資產 | E9: 流動資產
A10: 1151 | B10: 透過損益按公允價值衡量之金融資產-流動 | C10: 借 | D10: 資產 | E10: 流動資產
A11: 1154 | B11: 避險之金融資產-流動 | C11: 借 | D11: 資產 | E11: 流動資產
A12: 1158 | B12: 透過其他綜合損益按公允價值衡量之金融資產-流動 | C12: 借 | D12: 資產 | E12: 流動資產
... A138: 3600 | B138: 減:庫藏股票 | C138: 借 | D138: 權益 | E138: 股東權益
A139: 4100 | B139: 銷貨收入 | C139: 貸 | D139: 收入
A140: 4110 | B140: 減:銷貨退回 | C140: 借 | D140: 收入
A141: 4120 | B141: 減:銷貨折讓 | C141: 借 | D141: 收入
A142: 4200 | B142: 勞務收入 | C142: 貸 | D142: 收入
A143: 4300 | B143: 加工收入 | C143: 貸 | D143: 收入
A144: 4400 | B144: 工程收入 | C144: 貸 | D144: 收入
A145: 5100 | B145: 銷貨成本 | C145: 借 | D145: 銷貨成本
A146: 5200 | B146: 勞務成本 | C146: 借 | D146: 銷貨成本
A147: 5300 | B147: 加工成本 | C147: 借 | D147: 銷貨成本
A148: 5400 | B148: 工程成本 | C148: 借 | D148: 銷貨成本
A149: 6010 | B149: 薪資支出 | C149: 借 | D149: 費用
A150: 6020 | B150: 租金支出 | C150: 借 | D150: 費用
... A225: 9500 | B225: 本期其他綜合損益(稅後淨額) | C225: 借 | D225: 所得稅

Sheet 試算表
A1: 科目代號 | B1: 科目名稱 | C1: 借方合計 | D1: 貸方合計 | E1: 餘額 | F1: 科目類別 | G1: BS分類
A2: 1111 | B2: 零用金 | C2: =SUMIFS(日記簿!$F$2:$F$1000,日記簿!$D$2:$D$1000,A2) -> 0 | D2: =SUMIFS(日記簿!$G$2:$G$1000,日記簿!$D$2:$D$1000,A2) -> 0 | E2: =C2-D2 -> 0 | F2: 資產 | G2: 流動資產
A3: 1112 | B3: 銀行存款 | C3: =SUMIFS(日記簿!$F$2:$F$1000,日記簿!$D$2:$D$1000,A3) -> 0 | D3: =SUMIFS(日記簿!$G$2:$G$1000,日記簿!$D$2:$D$1000,A3) -> 0 | E3: =C3-D3 -> 0 | F3: 資產 | G3: 流動資產
A4: 11121 | B4: 銀行存款-國泰 | C4: =SUMIFS(日記簿!$F$2:$F$1000,日記簿!$D$2:$D$1000,A4) -> 19879 | D4: =SUMIFS(日記簿!$G$2:$G$1000,日記簿!$D$2:$D$1000,A4) -> 8782 | E4: =C4-D4 -> 11097 | F4: 資產 | G4: 流動資產
A5: 11122 | B5: 銀行存款-合庫 | C5: =SUMIFS(日記簿!$F$2:$F$1000,日記簿!$D$2:$D$1000,A5) -> 29835 | D5: =SUMIFS(日記簿!$G$2:$G$1000,日記簿!$D$2:$D$1000,A5) -> 28062 | E5: =C5-D5 -> 1773 | F5: 資產 | G5: 流動資產
A6: 11123 | B6: 銀行存款-台銀活存 | C6: =SUMIFS(日記簿!$F$2:$F$1000,日記簿!$D$2:$D$1000,A6) -> 0 | D6: =SUMIFS(日記簿!$G$2:$G$1000,日記簿!$D$2:$D$1000,A6) -> 0 | E6: =C6-D6 -> 0 | F6: 資產 | G6: 流動資產
A7: 11124 | B7: 銀行存款-台銀支存 | C7: =SUMIFS(日記簿!$F$2:$F$1000,日記簿!$D$2:$D$1000,A7) -> 0 | D7: =SUMIFS(日記簿!$G$2:$G$1000,日記簿!$D$2:$D$1000,A7) -> 0 | E7: =C7-D7 -> 0 | F7: 資產 | G7: 流動資產
A8: 1113 | B8: 約當現金 | C8: =SUMIFS(日記簿!$F$2:$F$1000,日記簿!$D$2:$D$1000,A8) -> 0 | D8: =SUMIFS(日記簿!$G$2:$G$1000,日記簿!$D$2:$D$1000,A8) -> 0 | E8: =C8-D8 -> 0 | F8: 資產 | G8: 流動資產
A9: 1114 | B9: 短期投資 | C9: =SUMIFS(日記簿!$F$2:$F$1000,日記簿!$D$2:$D$1000,A9) -> 0 | D9: =SUMIFS(日記簿!$G$2:$G$1000,日記簿!$D$2:$D$1000,A9) -> 0 | E9: =C9-D9 -> 0 | F9: 資產 | G9: 流動資產
A10: 1151 | B10: 透過損益按公允價值衡量之金融資產-流動 | C10: =SUMIFS(日記簿!$F$2:$F$1000,日記簿!$D$2:$D$1000,A10) -> 0 | D10: =SUMIFS(日記簿!$G$2:$G$1000,日記簿!$D$2:$D$1000,A10) -> 0 | E10: =C10-D10 -> 0 | F10: 資產 | G10: 流動資產
A11: 1154 | B11: 避險之金融資產-流動 | C11: =SUMIFS(日記簿!$F$2:$F$1000,日記簿!$D$2:$D$1000,A11) -> 0 | D11: =SUMIFS(日記簿!$G$2:$G$1000,日記簿!$D$2:$D$1000,A11) -> 0 | E11: =C11-D11 -> 0 | F11: 資產 | G11: 流動資產
A12: 1158 | B12: 透過其他綜合損益按公允價值衡量之金融資產-流動 | C12: =SUMIFS(日記簿!$F$2:$F$1000,日記簿!$D$2:$D$1000,A12) -> 0 | D12: =SUMIFS(日記簿!$G$2:$G$1000,日記簿!$D$2:$D$1000,A12) -> 0 | E12: =C12-D12 -> 0 | F12: 資產 | G12: 流動資產
A13: 1161 | B13: 按攤銷後成本衡量之金融資產－流動 | C13: =SUMIFS(日記簿!$F$2:$F$1000,日記簿!$D$2:$D$1000,A13) -> 0 | D13: =SUMIFS(日記簿!$G$2:$G$1000,日記簿!$D$2:$D$1000,A13) -> 0 | E13: =C13-D13 -> 0 | F13: 資產 | G13: 流動資產
A14: 1157 | B14: 其他金融資產-流動 | C14: =SUMIFS(日記簿!$F$2:$F$1000,日記簿!$D$2:$D$1000,A14) -> 0 | D14: =SUMIFS(日記簿!$G$2:$G$1000,日記簿!$D$2:$D$1000,A14) -> 0 | E14: =C14-D14 -> 0 | F14: 資產 | G14: 流動資產
A15: 1159 | B15: 減:累計減損-金融資產-流動 | C15: =SUMIFS(日記簿!$F$2:$F$1000,日記簿!$D$2:$D$1000,A15) -> 0 | D15: =SUMIFS(日記簿!$G$2:$G$1000,日記簿!$D$2:$D$1000,A15) -> 0 | E15: =D15-C15 -> 0 | F15: 資產 | G15: 流動資產
A16: 1125 | B16: 合約資產-流動 | C16: =SUMIFS(日記簿!$F$2:$F$1000,日記簿!$D$2:$D$1000,A16) -> 0 | D16: =SUMIFS(日記簿!$G$2:$G$1000,日記簿!$D$2:$D$1000,A16) -> 0 | E16: =C16-D16 -> 0 | F16: 資產 | G16: 流動資產
A17: 1126 | B17: 減:累計減損-合約資產-流動 | C17: =SUMIFS(日記簿!$F$2:$F$1000,日記簿!$D$2:$D$1000,A17) -> 0 | D17: =SUMIFS(日記簿!$G$2:$G$1000,日記簿!$D$2:$D$1000,A17) -> 0 | E17: =D17-C17 -> 0 | F17: 資產 | G17: 流動資產
A18: 1121 | B18: 應收票據 | C18: =SUMIFS(日記簿!$F$2:$F$1000,日記簿!$D$2:$D$1000,A18) -> 0 | D18: =SUMIFS(日記簿!$G$2:$G$1000,日記簿!$D$2:$D$1000,A18) -> 0 | E18: =C18-D18 -> 0 | F18: 資產 | G18: 流動資產
A19: 1122 | B19: 減:備抵呆帳-應收票據 | C19: =SUMIFS(日記簿!$F$2:$F$1000,日記簿!$D$2:$D$1000,A19) -> 0 | D19: =SUMIFS(日記簿!$G$2:$G$1000,日記簿!$D$2:$D$1000,A19) -> 0 | E19: =D19-C19 -> 0 | F19: 資產 | G19: 流動資產
A20: 1123 | B20: 應收帳款 | C20: =SUMIFS(日記簿!$F$2:$F$1000,日記簿!$D$2:$D$1000,A20) -> 2842717 | D20: =SUMIFS(日記簿!$G$2:$G$1000,日記簿!$D$2:$D$1000,A20) -> 2682788 | E20: =C20-D20 -> 159929 | F20: 資產 | G20: 流動資產
A21: 1124 | B21: 減:備抵呆帳-應收帳款 | C21: =SUMIFS(日記簿!$F$2:$F$1000,日記簿!$D$2:$D$1000,A21) -> 0 | D21: =SUMIFS(日記簿!$G$2:$G$1000,日記簿!$D$2:$D$1000,A21) -> 0 | E21: =D21-C21 -> 0 | F21: 資產 | G21: 流動資產
A22: 1129 | B22: 其他應收款 | C22: =SUMIFS(日記簿!$F$2:$F$1000,日記簿!$D$2:$D$1000,A22) -> 0 | D22: =SUMIFS(日記簿!$G$2:$G$1000,日記簿!$D$2:$D$1000,A22) -> 0 | E22: =C22-D22 -> 0 | F22: 資產 | G22: 流動資產
A23: 1131 | B23: 商品 | C23: =SUMIFS(日記簿!$F$2:$F$1000,日記簿!$D$2:$D$1000,A23) -> 0 | D23: =SUMIFS(日記簿!$G$2:$G$1000,日記簿!$D$2:$D$1000,A23) -> 0 | E23: =C23-D23 -> 0 | F23: 資產 | G23: 流動資產
A24: 1132 | B24: 製成品 | C24: =SUMIFS(日記簿!$F$2:$F$1000,日記簿!$D$2:$D$1000,A24) -> 0 | D24: =SUMIFS(日記簿!$G$2:$G$1000,日記簿!$D$2:$D$1000,A24) -> 0 | E24: =C24-D24 -> 0 | F24: 資產 | G24: 流動資產
A25: 1133 | B25: 在製品 | C25: =SUMIFS(日記簿!$F$2:$F$1000,日記簿!$D$2:$D$1000,A25) -> 0 | D25: =SUMIFS(日記簿!$G$2:$G$1000,日記簿!$D$2:$D$1000,A25) -> 0 | E25: =C25-D25 -> 0 | F25: 資產 | G25: 流動資產
A26: 1134 | B26: 原料 | C26: =SUMIFS(日記簿!$F$2:$F$1000,日記簿!$D$2:$D$1000,A26) -> 0 | D26: =SUMIFS(日記簿!$G$2:$G$1000,日記簿!$D$2:$D$1000,A26) -> 0 | E26: =C26-D26 -> 0 | F26: 資產 | G26: 流動資產
A27: 1135 | B27: 物料 | C27: =SUMIFS(日記簿!$F$2:$F$1000,日記簿!$D$2:$D$1000,A27) -> 0 | D27: =SUMIFS(日記簿!$G$2:$G$1000,日記簿!$D$2:$D$1000,A27) -> 0 | E27: =C27-D27 -> 0 | F27: 資產 | G27: 流動資產
A28: 1136 | B28: 寄銷品 | C28: =SUMIFS(日記簿!$F$2:$F$1000,日記簿!$D$2:$D$1000,A28) -> 0 | D28: =SUMIFS(日記簿!$G$2:$G$1000,日記簿!$D$2:$D$1000,A28) -> 0 | E28: =C28-D28 -> 0 | F28: 資產 | G28: 流動資產
A29: 1138 | B29: 其他存貨 | C29: =SUMIFS(日記簿!$F$2:$F$1000,日記簿!$D$2:$D$1000,A29) -> 0 | D29: =SUMIFS(日記簿!$G$2:$G$1000,日記簿!$D$2:$D$1000,A29) -> 0 | E29: =C29-D29 -> 0 | F29: 資產 | G29: 流動資產
A30: 1137 | B30: 備抵存貨跌價損失 | C30: =SUMIFS(日記簿!$F$2:$F$1000,日記簿!$D$2:$D$1000,A30) -> 0 | D30: =SUMIFS(日記簿!$G$2:$G$1000,日記簿!$D$2:$D$1000,A30) -> 0 | E30: =D30-C30 -> 0 | F30: 資產 | G30: 流動資產
A31: 1141 | B31: 預付費用 | C31: =SUMIFS(日記簿!$F$2:$F$1000,日記簿!$D$2:$D$1000,A31) -> 0 | D31: =SUMIFS(日記簿!$G$2:$G$1000,日記簿!$D$2:$D$1000,A31) -> 0 | E31: =C31-D31 -> 0 | F31: 資產 | G31: 流動資產
A32: 1142 | B32: 用品盤存 | C32: =SUMIFS(日記簿!$F$2:$F$1000,日記簿!$D$2:$D$1000,A32) -> 0 | D32: =SUMIFS(日記簿!$G$2:$G$1000,日記簿!$D$2:$D$1000,A32) -> 0 | E32: =C32-D32 -> 0 | F32: 資產 | G32: 流動資產
A33: 1143 | B33: 預付貨款 | C33: =SUMIFS(日記簿!$F$2:$F$1000,日記簿!$D$2:$D$1000,A33) -> 0 | D33: =SUMIFS(日記簿!$G$2:$G$1000,日記簿!$D$2:$D$1000,A33) -> 0 | E33: =C33-D33 -> 0 | F33: 資產 | G33: 流動資產
A34: 1144 | B34: 進項稅額 | C34: =SUMIFS(日記簿!$F$2:$F$1000,日記簿!$D$2:$D$1000,A34) -> 76948 | D34: =SUMIFS(日記簿!$G$2:$G$1000,日記簿!$D$2:$D$1000,A34) -> 60435 | E34: =C34-D34 -> 16513 | F34: 資產 | G34: 流動資產
A35: 1145 | B35: 留抵稅額 | C35: =SUMIFS(日記簿!$F$2:$F$1000,日記簿!$D$2:$D$1000,A35) -> 0 | D35: =SUMIFS(日記簿!$G$2:$G$1000,日記簿!$D$2:$D$1000,A35) -> 0 | E35: =C35-D35 -> 0 | F35: 資產 | G35: 流動資產
A36: 1149 | B36: 其他預付款 | C36: =SUMIFS(日記簿!$F$2:$F$1000,日記簿!$D$2:$D$1000,A36) -> 0 | D36: =SUMIFS(日記簿!$G$2:$G$1000,日記簿!$D$2:$D$1000,A36) -> 0 | E36: =C36-D36 -> 0 | F36: 資產 | G36: 流動資產
A37: 1191 | B37: 暫付款 | C37: =SUMIFS(日記簿!$F$2:$F$1000,日記簿!$D$2:$D$1000,A37) -> 0 | D37: =SUMIFS(日記簿!$G$2:$G$1000,日記簿!$D$2:$D$1000,A37) -> 0 | E37: =C37-D37 -> 0 | F37: 資產 | G37: 流動資產
A38: 1192 | B38: 股東往來 | C38: =SUMIFS(日記簿!$F$2:$F$1000,日記簿!$D$2:$D$1000,A38) -> 2 | D38: =SUMIFS(日記簿!$G$2:$G$1000,日記簿!$D$2:$D$1000,A38) -> 2 | E38: =C38-D38 -> 0 | F38: 資產 | G38: 流動資產
A39: 1193 | B39: 同業往來 | C39: =SUMIFS(日記簿!$F$2:$F$1000,日記簿!$D$2:$D$1000,A39) -> 0 | D39: =SUMIFS(日記簿!$G$2:$G$1000,日記簿!$D$2:$D$1000,A39) -> 0 | E39: =C39-D39 -> 0 | F39: 資產 | G39: 流動資產
A40: 1199 | B40: 其他流動資產-其他 | C40: =SUMIFS(日記簿!$F$2:$F$1000,日記簿!$D$2:$D$1000,A40) -> 0 | D40: =SUMIFS(日記簿!$G$2:$G$1000,日記簿!$D$2:$D$1000,A40) -> 0 | E40: =C40-D40 -> 0 | F40: 資產 | G40: 流動資產
A41: 1300 | B41: 長期性之投資 | C41: =SUMIFS(日記簿!$F$2:$F$1000,日記簿!$D$2:$D$1000,A41) -> 0 | D41: =SUMIFS(日記簿!$G$2:$G$1000,日記簿!$D$2:$D$1000,A41) -> 0 | E41: =C41-D41 -> 0 | F41: 資產 | G41: 流動資產
A42: 1415 | B42: 減:累計減損-長期性之投資 | C42: =SUMIFS(日記簿!$F$2:$F$1000,日記簿!$D$2:$D$1000,A42) -> 0 | D42: =SUMIFS(日記簿!$G$2:$G$1000,日記簿!$D$2:$D$1000,A42) -> 0 | E42: =D42-C42 -> 0 | F42: 資產 | G42: 非流動資產
A43: 1612 | B43: 透過損益按公允價值衡量之金融資產-非流動 | C43: =SUMIFS(日記簿!$F$2:$F$1000,日記簿!$D$2:$D$1000,A43) -> 0 | D43: =SUMIFS(日記簿!$G$2:$G$1000,日記簿!$D$2:$D$1000,A43) -> 0 | E43: =C43-D43 -> 0 | F43: 資產 | G43: 非流動資產
A44: 1615 | B44: 避險之金融資產-非流動 | C44: =SUMIFS(日記簿!$F$2:$F$1000,日記簿!$D$2:$D$1000,A44) -> 0 | D44: =SUMIFS(日記簿!$G$2:$G$1000,日記簿!$D$2:$D$1000,A44) -> 0 | E44: =C44-D44 -> 0 | F44: 資產 | G44: 非流動資產
A45: 1621 | B45: 透過其他綜合損益按公允價值衡量之金融資產-非流動 | C45: =SUMIFS(日記簿!$F$2:$F$1000,日記簿!$D$2:$D$1000,A45) -> 0 | D45: =SUMIFS(日記簿!$G$2:$G$1000,日記簿!$D$2:$D$1000,A45) -> 0 | E45: =C45-D45 -> 0 | F45: 資產 | G45: 非流動資產
A46: 1622 | B46: 按攤銷後成本衡量之金融資產－非流動 | C46: =SUMIFS(日記簿!$F$2:$F$1000,日記簿!$D$2:$D$1000,A46) -> 0 | D46: =SUMIFS(日記簿!$G$2:$G$1000,日記簿!$D$2:$D$1000,A46) -> 0 | E46: =C46-D46 -> 0 | F46: 資產 | G46: 非流動資產
A47: 1618 | B47: 其他金融資產-非流動 | C47: =SUMIFS(日記簿!$F$2:$F$1000,日記簿!$D$2:$D$1000,A47) -> 0 | D47: =SUMIFS(日記簿!$G$2:$G$1000,日記簿!$D$2:$D$1000,A47) -> 0 | E47: =C47-D47 -> 0 | F47: 資產 | G47: 非流動資產
A48: 1630 | B48: 採用權益法之投資 | C48: =SUMIFS(日記簿!$F$2:$F$1000,日記簿!$D$2:$D$1000,A48) -> 0 | D48: =SUMIFS(日記簿!$G$2:$G$1000,日記簿!$D$2:$D$1000,A48) -> 0 | E48: =C48-D48 -> 0 | F48: 資產 | G48: 非流動資產
A49: 1631 | B49: 減:累計減損-金融資產-非流動 | C49: =SUMIFS(日記簿!$F$2:$F$1000,日記簿!$D$2:$D$1000,A49) -> 0 | D49: =SUMIFS(日記簿!$G$2:$G$1000,日記簿!$D$2:$D$1000,A49) -> 0 | E49: =D49-C49 -> 0 | F49: 資產 | G49: 非流動資產
A50: 1640 | B50: 合約資產-非流動 | C50: =SUMIFS(日記簿!$F$2:$F$1000,日記簿!$D$2:$D$1000,A50) -> 0 | D50: =SUMIFS(日記簿!$G$2:$G$1000,日記簿!$D$2:$D$1000,A50) -> 0 | E50: =C50-D50 -> 0 | F50: 資產 | G50: 非流動資產
A51: 1641 | B51: 減:累計減損-合約資產-非流動 | C51: =SUMIFS(日記簿!$F$2:$F$1000,日記簿!$D$2:$D$1000,A51) -> 0 | D51: =SUMIFS(日記簿!$G$2:$G$1000,日記簿!$D$2:$D$1000,A51) -> 0 | E51: =D51-C51 -> 0 | F51: 資產 | G51: 非流動資產
A52: 1410 | B52: 土地 | C52: =SUMIFS(日記簿!$F$2:$F$1000,日記簿!$D$2:$D$1000,A52) -> 0 | D52: =SUMIFS(日記簿!$G$2:$G$1000,日記簿!$D$2:$D$1000,A52) -> 0 | E52: =C52-D52 -> 0 | F52: 資產 | G52: 非流動資產
A53: 1411 | B53: 減:累計減損-土地 | C53: =SUMIFS(日記簿!$F$2:$F$1000,日記簿!$D$2:$D$1000,A53) -> 0 | D53: =SUMIFS(日記簿!$G$2:$G$1000,日記簿!$D$2:$D$1000,A53) -> 0 | E53: =D53-C53 -> 0 | F53: 資產 | G53: 非流動資產
A54: 1431 | B54: 房屋及建築 | C54: =SUMIFS(日記簿!$F$2:$F$1000,日記簿!$D$2:$D$1000,A54) -> 0 | D54: =SUMIFS(日記簿!$G$2:$G$1000,日記簿!$D$2:$D$1000,A54) -> 0 | E54: =C54-D54 -> 0 | F54: 資產 | G54: 非流動資產
A55: 1432 | B55: 減:累計折舊-房屋及建築 | C55: =SUMIFS(日記簿!$F$2:$F$1000,日記簿!$D$2:$D$1000,A55) -> 0 | D55: =SUMIFS(日記簿!$G$2:$G$1000,日記簿!$D$2:$D$1000,A55) -> 0 | E55: =D55-C55 -> 0 | F55: 資產 | G55: 非流動資產
A56: 1433 | B56: 減:累計減損-房屋及建築 | C56: =SUMIFS(日記簿!$F$2:$F$1000,日記簿!$D$2:$D$1000,A56) -> 0 | D56: =SUMIFS(日記簿!$G$2:$G$1000,日記簿!$D$2:$D$1000,A56) -> 0 | E56: =D56-C56 -> 0 | F56: 資產 | G56: 非流動資產
A57: 1441 | B57: 機器設備 | C57: =SUMIFS(日記簿!$F$2:$F$1000,日記簿!$D$2:$D$1000,A57) -> 0 | D57: =SUMIFS(日記簿!$G$2:$G$1000,日記簿!$D$2:$D$1000,A57) -> 0 | E57: =C57-D57 -> 0 | F57: 資產 | G57: 非流動資產
A58: 1442 | B58: 減:累計折舊-機器設備 | C58: =SUMIFS(日記簿!$F$2:$F$1000,日記簿!$D$2:$D$1000,A58) -> 0 | D58: =SUMIFS(日記簿!$G$2:$G$1000,日記簿!$D$2:$D$1000,A58) -> 0 | E58: =D58-C58 -> 0 | F58: 資產 | G58: 非流動資產
A59: 1443 | B59: 減:累計減損-機器設備 | C59: =SUMIFS(日記簿!$F$2:$F$1000,日記簿!$D$2:$D$1000,A59) -> 0 | D59: =SUMIFS(日記簿!$G$2:$G$1000,日記簿!$D$2:$D$1000,A59) -> 0 | E59: =D59-C59 -> 0 | F59: 資產 | G59: 非流動資產
A60: 1451 | B60: 運輸設備 | C60: =SUMIFS(日記簿!$F$2:$F$1000,日記簿!$D$2:$D$1000,A60) -> 0 | D60: =SUMIFS(日記簿!$G$2:$G$1000,日記簿!$D$2:$D$1000,A60) -> 0 | E60: =C60-D60 -> 0 | F60: 資產 | G60: 非流動資產
A61: 1452 | B61: 減:累計折舊-運輸設備 | C61: =SUMIFS(日記簿!$F$2:$F$1000,日記簿!$D$2:$D$1000,A61) -> 0 | D61: =SUMIFS(日記簿!$G$2:$G$1000,日記簿!$D$2:$D$1000,A61) -> 0 | E61: =D61-C61 -> 0 | F61: 資產 | G61: 非流動資產
A62: 1453 | B62: 減:累計減損-運輸設備 | C62: =SUMIFS(日記簿!$F$2:$F$1000,日記簿!$D$2:$D$1000,A62) -> 0 | D62: =SUMIFS(日記簿!$G$2:$G$1000,日記簿!$D$2:$D$1000,A62) -> 0 | E62: =D62-C62 -> 0 | F62: 資產 | G62: 非流動資產
A63: 1461 | B63: 生財器具 | C63: =SUMIFS(日記簿!$F$2:$F$1000,日記簿!$D$2:$D$1000,A63) -> 344800 | D63: =SUMIFS(日記簿!$G$2:$G$1000,日記簿!$D$2:$D$1000,A63) -> 0 | E63: =C63-D63 -> 344800 | F63: 資產 | G63: 非流動資產
A64: 1462 | B64: 減:累計折舊-生財器具 | C64: =SUMIFS(日記簿!$F$2:$F$1000,日記簿!$D$2:$D$1000,A64) -> 0 | D64: =SUMIFS(日記簿!$G$2:$G$1000,日記簿!$D$2:$D$1000,A64) -> 106250 | E64: =D64-C64 -> 106250 | F64: 資產 | G64: 非流動資產
A65: 1463 | B65: 減:累計減損-生財器具 | C65: =SUMIFS(日記簿!$F$2:$F$1000,日記簿!$D$2:$D$1000,A65) -> 0 | D65: =SUMIFS(日記簿!$G$2:$G$1000,日記簿!$D$2:$D$1000,A65) -> 0 | E65: =D65-C65 -> 0 | F65: 資產 | G65: 非流動資產
A66: 1470 | B66: 未完工程及待驗設備 | C66: =SUMIFS(日記簿!$F$2:$F$1000,日記簿!$D$2:$D$1000,A66) -> 0 | D66: =SUMIFS(日記簿!$G$2:$G$1000,日記簿!$D$2:$D$1000,A66) -> 0 | E66: =C66-D66 -> 0 | F66: 資產 | G66: 非流動資產
A67: 1580 | B67: 預付購置設備款 | C67: =SUMIFS(日記簿!$F$2:$F$1000,日記簿!$D$2:$D$1000,A67) -> 0 | D67: =SUMIFS(日記簿!$G$2:$G$1000,日記簿!$D$2:$D$1000,A67) -> 0 | E67: =C67-D67 -> 0 | F67: 資產 | G67: 非流動資產
A68: 1491 | B68: 其他固定資產 | C68: =SUMIFS(日記簿!$F$2:$F$1000,日記簿!$D$2:$D$1000,A68) -> 0 | D68: =SUMIFS(日記簿!$G$2:$G$1000,日記簿!$D$2:$D$1000,A68) -> 0 | E68: =C68-D68 -> 0 | F68: 資產 | G68: 非流動資產
A69: 1492 | B69: 減:累計折舊-其他固定資產 | C69: =SUMIFS(日記簿!$F$2:$F$1000,日記簿!$D$2:$D$1000,A69) -> 0 | D69: =SUMIFS(日記簿!$G$2:$G$1000,日記簿!$D$2:$D$1000,A69) -> 0 | E69: =D69-C69 -> 0 | F69: 資產 | G69: 非流動資產
A70: 1493 | B70: 減:累計減損-其他固定資產 | C70: =SUMIFS(日記簿!$F$2:$F$1000,日記簿!$D$2:$D$1000,A70) -> 0 | D70: =SUMIFS(日記簿!$G$2:$G$1000,日記簿!$D$2:$D$1000,A70) -> 0 | E70: =D70-C70 -> 0 | F70: 資產 | G70: 非流動資產
A71: 1541 | B71: 投資性不動產 | C71: =SUMIFS(日記簿!$F$2:$F$1000,日記簿!$D$2:$D$1000,A71) -> 0 | D71: =SUMIFS(日記簿!$G$2:$G$1000,日記簿!$D$2:$D$1000,A71) -> 0 | E71: =C71-D71 -> 0 | F71: 資產 | G71: 非流動資產
A72: 1542 | B72: 減:累計折舊-投資性不動產 | C72: =SUMIFS(日記簿!$F$2:$F$1000,日記簿!$D$2:$D$1000,A72) -> 0 | D72: =SUMIFS(日記簿!$G$2:$G$1000,日記簿!$D$2:$D$1000,A72) -> 0 | E72: =D72-C72 -> 0 | F72: 資產 | G72: 非流動資產
A73: 1421 | B73: 礦產資源 | C73: =SUMIFS(日記簿!$F$2:$F$1000,日記簿!$D$2:$D$1000,A73) -> 0 | D73: =SUMIFS(日記簿!$G$2:$G$1000,日記簿!$D$2:$D$1000,A73) -> 0 | E73: =C73-D73 -> 0 | F73: 資產 | G73: 非流動資產
A74: 1422 | B74: 減:累計折耗-礦產資源 | C74: =SUMIFS(日記簿!$F$2:$F$1000,日記簿!$D$2:$D$1000,A74) -> 0 | D74: =SUMIFS(日記簿!$G$2:$G$1000,日記簿!$D$2:$D$1000,A74) -> 0 | E74: =D74-C74 -> 0 | F74: 資產 | G74: 非流動資產
A75: 1551 | B75: 生物資產 | C75: =SUMIFS(日記簿!$F$2:$F$1000,日記簿!$D$2:$D$1000,A75) -> 0 | D75: =SUMIFS(日記簿!$G$2:$G$1000,日記簿!$D$2:$D$1000,A75) -> 0 | E75: =C75-D75 -> 0 | F75: 資產 | G75: 非流動資產
A76: 1552 | B76: 減:累計折舊-生物資產 | C76: =SUMIFS(日記簿!$F$2:$F$1000,日記簿!$D$2:$D$1000,A76) -> 0 | D76: =SUMIFS(日記簿!$G$2:$G$1000,日記簿!$D$2:$D$1000,A76) -> 0 | E76: =D76-C76 -> 0 | F76: 資產 | G76: 非流動資產
A77: 1553 | B77: 減:累計減損-生物資產 | C77: =SUMIFS(日記簿!$F$2:$F$1000,日記簿!$D$2:$D$1000,A77) -> 0 | D77: =SUMIFS(日記簿!$G$2:$G$1000,日記簿!$D$2:$D$1000,A77) -> 0 | E77: =D77-C77 -> 0 | F77: 資產 | G77: 非流動資產
A78: 1510 | B78: 無形資產 | C78: =SUMIFS(日記簿!$F$2:$F$1000,日記簿!$D$2:$D$1000,A78) -> 0 | D78: =SUMIFS(日記簿!$G$2:$G$1000,日記簿!$D$2:$D$1000,A78) -> 0 | E78: =C78-D78 -> 0 | F78: 資產 | G78: 非流動資產
A79: 1511 | B79: 減:累計攤折-無形資產 | C79: =SUMIFS(日記簿!$F$2:$F$1000,日記簿!$D$2:$D$1000,A79) -> 0 | D79: =SUMIFS(日記簿!$G$2:$G$1000,日記簿!$D$2:$D$1000,A79) -> 0 | E79: =D79-C79 -> 0 | F79: 資產 | G79: 非流動資產
A80: 1512 | B80: 減:累計減損-無形資產 | C80: =SUMIFS(日記簿!$F$2:$F$1000,日記簿!$D$2:$D$1000,A80) -> 0 | D80: =SUMIFS(日記簿!$G$2:$G$1000,日記簿!$D$2:$D$1000,A80) -> 0 | E80: =D80-C80 -> 0 | F80: 資產 | G80: 非流動資產
A81: 1901 | B81: 存出保證金 | C81: =SUMIFS(日記簿!$F$2:$F$1000,日記簿!$D$2:$D$1000,A81) -> 50000 | D81: =SUMIFS(日記簿!$G$2:$G$1000,日記簿!$D$2:$D$1000,A81) -> 0 | E81: =C81-D81 -> 50000 | F81: 資產 | G81: 非流動資產
A82: 1902 | B82: 未攤銷費用 | C82: =SUMIFS(日記簿!$F$2:$F$1000,日記簿!$D$2:$D$1000,A82) -> 0 | D82: =SUMIFS(日記簿!$G$2:$G$1000,日記簿!$D$2:$D$1000,A82) -> 0 | E82: =C82-D82 -> 0 | F82: 資產 | G82: 非流動資產
A83: 1903 | B83: 預付設備款 | C83: =SUMIFS(日記簿!$F$2:$F$1000,日記簿!$D$2:$D$1000,A83) -> 0 | D83: =SUMIFS(日記簿!$G$2:$G$1000,日記簿!$D$2:$D$1000,A83) -> 0 | E83: =C83-D83 -> 0 | F83: 資產 | G83: 非流動資產
A84: 1904 | B84: 其他非流動資產-其他 | C84: =SUMIFS(日記簿!$F$2:$F$1000,日記簿!$D$2:$D$1000,A84) -> 0 | D84: =SUMIFS(日記簿!$G$2:$G$1000,日記簿!$D$2:$D$1000,A84) -> 0 | E84: =C84-D84 -> 0 | F84: 資產 | G84: 非流動資產
A85: 2111 | B85: 銀行透支 | C85: =SUMIFS(日記簿!$F$2:$F$1000,日記簿!$D$2:$D$1000,A85) -> 0 | D85: =SUMIFS(日記簿!$G$2:$G$1000,日記簿!$D$2:$D$1000,A85) -> 0 | E85: =D85-C85 -> 0 | F85: 負債 | G85: 流動負債
A86: 2112 | B86: 銀行借款 | C86: =SUMIFS(日記簿!$F$2:$F$1000,日記簿!$D$2:$D$1000,A86) -> 254360 | D86: =SUMIFS(日記簿!$G$2:$G$1000,日記簿!$D$2:$D$1000,A86) -> 425360 | E86: =D86-C86 -> 171000 | F86: 負債 | G86: 流動負債
A87: 2113 | B87: 應付短期票券 | C87: =SUMIFS(日記簿!$F$2:$F$1000,日記簿!$D$2:$D$1000,A87) -> 0 | D87: =SUMIFS(日記簿!$G$2:$G$1000,日記簿!$D$2:$D$1000,A87) -> 0 | E87: =D87-C87 -> 0 | F87: 負債 | G87: 流動負債
A88: 2119 | B88: 其他短期借款 | C88: =SUMIFS(日記簿!$F$2:$F$1000,日記簿!$D$2:$D$1000,A88) -> 0 | D88: =SUMIFS(日記簿!$G$2:$G$1000,日記簿!$D$2:$D$1000,A88) -> 0 | E88: =D88-C88 -> 0 | F88: 負債 | G88: 流動負債
A89: 2140 | B89: 透過損益按公允價值衡量之金融負債-流動 | C89: =SUMIFS(日記簿!$F$2:$F$1000,日記簿!$D$2:$D$1000,A89) -> 0 | D89: =SUMIFS(日記簿!$G$2:$G$1000,日記簿!$D$2:$D$1000,A89) -> 0 | E89: =D89-C89 -> 0 | F89: 負債 | G89: 流動負債
A90: 2150 | B90: 避險之金融負債-流動 | C90: =SUMIFS(日記簿!$F$2:$F$1000,日記簿!$D$2:$D$1000,A90) -> 0 | D90: =SUMIFS(日記簿!$G$2:$G$1000,日記簿!$D$2:$D$1000,A90) -> 0 | E90: =D90-C90 -> 0 | F90: 負債 | G90: 流動負債
A91: 2170 | B91: 特別股負債-流動 | C91: =SUMIFS(日記簿!$F$2:$F$1000,日記簿!$D$2:$D$1000,A91) -> 0 | D91: =SUMIFS(日記簿!$G$2:$G$1000,日記簿!$D$2:$D$1000,A91) -> 0 | E91: =D91-C91 -> 0 | F91: 負債 | G91: 流動負債
A92: 2180 | B92: 其他金融負債-流動 | C92: =SUMIFS(日記簿!$F$2:$F$1000,日記簿!$D$2:$D$1000,A92) -> 0 | D92: =SUMIFS(日記簿!$G$2:$G$1000,日記簿!$D$2:$D$1000,A92) -> 0 | E92: =D92-C92 -> 0 | F92: 負債 | G92: 流動負債
A93: 2126 | B93: 合約負債-流動 | C93: =SUMIFS(日記簿!$F$2:$F$1000,日記簿!$D$2:$D$1000,A93) -> 0 | D93: =SUMIFS(日記簿!$G$2:$G$1000,日記簿!$D$2:$D$1000,A93) -> 0 | E93: =D93-C93 -> 0 | F93: 負債 | G93: 流動負債
A94: 2120 | B94: 應付票據 | C94: =SUMIFS(日記簿!$F$2:$F$1000,日記簿!$D$2:$D$1000,A94) -> 0 | D94: =SUMIFS(日記簿!$G$2:$G$1000,日記簿!$D$2:$D$1000,A94) -> 0 | E94: =D94-C94 -> 0 | F94: 負債 | G94: 流動負債
A95: 2121 | B95: 應付帳款 | C95: =SUMIFS(日記簿!$F$2:$F$1000,日記簿!$D$2:$D$1000,A95) -> 2236844 | D95: =SUMIFS(日記簿!$G$2:$G$1000,日記簿!$D$2:$D$1000,A95) -> 3335955 | E95: =D95-C95 -> 1099111 | F95: 負債 | G95: 流動負債
A96: 2131 | B96: 應付費用 | C96: =SUMIFS(日記簿!$F$2:$F$1000,日記簿!$D$2:$D$1000,A96) -> 0 | D96: =SUMIFS(日記簿!$G$2:$G$1000,日記簿!$D$2:$D$1000,A96) -> 0 | E96: =D96-C96 -> 0 | F96: 負債 | G96: 流動負債
... A137: 3506 | B137: 其他權益-其他 | C137: =SUMIFS(日記簿!$F$2:$F$1000,日記簿!$D$2:$D$1000,A137) -> 0 | D137: =SUMIFS(日記簿!$G$2:$G$1000,日記簿!$D$2:$D$1000,A137) -> 0 | E137: =D137-C137 -> 0 | F137: 權益 | G137: 股東權益
A138: 3600 | B138: 減:庫藏股票 | C138: =SUMIFS(日記簿!$F$2:$F$1000,日記簿!$D$2:$D$1000,A138) -> 0 | D138: =SUMIFS(日記簿!$G$2:$G$1000,日記簿!$D$2:$D$1000,A138) -> 0 | E138: =C138-D138 -> 0 | F138: 權益 | G138: 股東權益
A139: 4100 | B139: 銷貨收入 | C139: =SUMIFS(日記簿!$F$2:$F$1000,日記簿!$D$2:$D$1000,A139) -> 217547 | D139: =SUMIFS(日記簿!$G$2:$G$1000,日記簿!$D$2:$D$1000,A139) -> 2707340 | E139: =D139-C139 -> 2489793 | F139: 收入
A140: 4110 | B140: 減:銷貨退回 | C140: =SUMIFS(日記簿!$F$2:$F$1000,日記簿!$D$2:$D$1000,A140) -> 0 | D140: =SUMIFS(日記簿!$G$2:$G$1000,日記簿!$D$2:$D$1000,A140) -> 0 | E140: =C140-D140 -> 0 | F140: 收入
...

Sheet 日記簿
A1: 傳票號 | B1: 日期 | C1: 摘要 | D1: 科目代號 | E1: 科目名稱 | F1: 借方金額 | G1: 貸方金額
A2: 20250101001 | B2: 2025/01/01 | D2: 11121 | E2: =IFERROR(VLOOKUP(D2,科目表!$A:$B,2,FALSE),"") -> 銀行存款-國泰 | F2: 0
A3: 20250101001 | B3: 2025/01/01 | D3: 3110 | E3: =IFERROR(VLOOKUP(D3,科目表!$A:$B,2,FALSE),"") -> 實收資本 | G3: 0
A4: 20250101001 | B4: 2025/01/01 | C4: 開帳 | D4: 11121 | E4: =IF(D4="","",IFERROR(VLOOKUP(TEXT(D4,"0"),科目表!$A:$B,2,FALSE),"")) -> 銀行存款-國泰 | F4: 19879
A5: 20250101001 | B5: 2025/01/01 | C5: 開帳 | D5: 11122 | E5: =IF(D5="","",IFERROR(VLOOKUP(TEXT(D5,"0"),科目表!$A:$B,2,FALSE),"")) -> 銀行存款-合庫 | F5: 29835
A6: 20250101001 | B6: 2025/01/01 | C6: 開帳 | D6: 1144 | E6: =IF(D6="","",IFERROR(VLOOKUP(TEXT(D6,"0"),科目表!$A:$B,2,FALSE),"")) -> 進項稅額 | F6: 11794
A7: 20250101001 | B7: 2025/01/01 | C7: 開帳 | D7: 1461 | E7: =IF(D7="","",IFERROR(VLOOKUP(TEXT(D7,"0"),科目表!$A:$B,2,FALSE),"")) -> 生財器具 | F7: 300000
A8: 20250101001 | B8: 2025/01/01 | C8: 開帳 | D8: 1462 | E8: =IF(D8="","",IFERROR(VLOOKUP(TEXT(D8,"0"),科目表!$A:$B,2,FALSE),"")) -> 減:累計折舊-生財器具 | G8: 106250
A9: 20250101001 | B9: 2025/01/01 | C9: 開帳 | D9: 1901 | E9: =IF(D9="","",IFERROR(VLOOKUP(TEXT(D9,"0"),科目表!$A:$B,2,FALSE),"")) -> 存出保證金 | F9: 50000
A10: 20250101001 | B10: 2025/01/01 | C10: 開帳 | D10: 2112 | E10: =IF(D10="","",IFERROR(VLOOKUP(TEXT(D10,"0"),科目表!$A:$B,2,FALSE),"")) -> 銀行借款 | G10: 425360
A11: 20250101001 | B11: 2025/01/01 | C11: 開帳 | D11: 2121 | E11: =IF(D11="","",IFERROR(VLOOKUP(TEXT(D11,"0"),科目表!$A:$B,2,FALSE),"")) -> 應付帳款 | G11: 796077
A12: 20250101001 | B12: 2025/01/01 | C12: 開帳 | D12: 1192 | E12: =IF(D12="","",IFERROR(VLOOKUP(TEXT(D12,"0"),科目表!$A:$B,2,FALSE),"")) -> 股東往來 | F12: 1 | G12: 1
A13: 20250101001 | B13: 2025/01/01 | C13: 開帳 | D13: 2134 | E13: =IF(D13="","",IFERROR(VLOOKUP(TEXT(D13,"0"),科目表!$A:$B,2,FALSE),"")) -> 銷項稅額 | G13: 12952
A14: 20250101001 | B14: 2025/01/01 | C14: 開帳 | D14: 3430 | E14: =IF(D14="","",IFERROR(VLOOKUP(TEXT(D14,"0"),科目表!$A:$B,2,FALSE),"")) -> 累積盈虧 | F14: 1 | G14: 1
A15: 20250101001 | B15: 2025/01/01 | C15: 開帳 | D15: 1192 | E15: =IF(D15="","",IFERROR(VLOOKUP(TEXT(D15,"0"),科目表!$A:$B,2,FALSE),"")) -> 股東往來 | F15: 1 | G15: 1
A16: 20250101001 | B16: 2025/01/01 | C16: 開帳 | D16: 3110 | E16: =IF(D16="","",IFERROR(VLOOKUP(TEXT(D16,"0"),科目表!$A:$B,2,FALSE),"")) -> 實收資本 | F16: -1000000
A17: 20250101001 | B17: 2025/01/01 | C17: 開帳 | D17: 3430 | E17: =IF(D17="","",IFERROR(VLOOKUP(TEXT(D17,"0"),科目表!$A:$B,2,FALSE),"")) -> 累積盈虧 | F17: 1 | G17: 1
A18: 20250101001 | B18: 2025/01/01 | C18: 開帳 | D18: 3430 | E18: =IF(D18="","",IFERROR(VLOOKUP(TEXT(D18,"0"),科目表!$A:$B,2,FALSE),"")) -> 累積盈虧 | F18: 1 | G18: 1
A19: 20250101001 | B19: 2025/01/01 | C19: 開帳 | D19: 3430 | E19: =IF(D19="","",IFERROR(VLOOKUP(TEXT(D19,"0"),科目表!$A:$B,2,FALSE),"")) -> 累積盈虧 | G19: -1929131
E20: =IF(D20="","",IFERROR(VLOOKUP(TEXT(D20,"0"),科目表!$A:$B,2,FALSE),""))
E21: =IF(D21="","",IFERROR(VLOOKUP(TEXT(D21,"0"),科目表!$A:$B,2,FALSE),""))
C22: 11-12月營業稅 | D22: 1144 | E22: =IF(D22="","",IFERROR(VLOOKUP(TEXT(D22,"0"),科目表!$A:$B,2,FALSE),"")) -> 進項稅額 | G22: 11794
C23: 11-12月營業稅 | D23: 2134 | E23: =IF(D23="","",IFERROR(VLOOKUP(TEXT(D23,"0"),科目表!$A:$B,2,FALSE),"")) -> 銷項稅額 | F23: 12952
C24: 11-12月營業稅 | D24: 2121 | E24: =IF(D24="","",IFERROR(VLOOKUP(TEXT(D24,"0"),科目表!$A:$B,2,FALSE),"")) -> 應付帳款 | G24: 1158
C25: 1-2月份 | D25: 4100 | E25: =IF(D25="","",IFERROR(VLOOKUP(TEXT(D25,"0"),科目表!$A:$B,2,FALSE),"")) -> 銷貨收入 | G25: 164159
C26: 1-2月份 | D26: 2134 | E26: =IF(D26="","",IFERROR(VLOOKUP(TEXT(D26,"0"),科目表!$A:$B,2,FALSE),"")) -> 銷項稅額 | G26: 8209
C27: 1-2月份 | D27: 1123 | E27: =IF(D27="","",IFERROR(VLOOKUP(TEXT(D27,"0"),科目表!$A:$B,2,FALSE),"")) -> 應收帳款 | F27: 1 | G27: 1
C28: 1-2月份 | D28: 1123 | E28: =IF(D28="","",IFERROR(VLOOKUP(TEXT(D28,"0"),科目表!$A:$B,2,FALSE),"")) -> 應收帳款 | F28: 172368
C29: 1-2月份 | D29: 5100 | E29: =IF(D29="","",IFERROR(VLOOKUP(TEXT(D29,"0"),科目表!$A:$B,2,FALSE),"")) -> 銷貨成本 | F29: 116244
C30: 1-2月份 | D30: 1144 | E30: =IF(D30="","",IFERROR(VLOOKUP(TEXT(D30,"0"),科目表!$A:$B,2,FALSE),"")) -> 進項稅額 | F30: 5809
C31: 1-2月份 | D31: 2121 | E31: =IF(D31="","",IFERROR(VLOOKUP(TEXT(D31,"0"),科目表!$A:$B,2,FALSE),"")) -> 應付帳款 | G31: 122053
C32: 1-2月份 | D32: 1144 | E32: =IF(D32="","",IFERROR(VLOOKUP(TEXT(D32,"0"),科目表!$A:$B,2,FALSE),"")) -> 進項稅額 | G32: 5809
C33: 1-2月份 | D33: 2134 | E33: =IF(D33="","",IFERROR(VLOOKUP(TEXT(D33,"0"),科目表!$A:$B,2,FALSE),"")) -> 銷項稅額 | F33: 8209
C34: 1-2月份營業稅 | D34: 2121 | E34: =IF(D34="","",IFERROR(VLOOKUP(TEXT(D34,"0"),科目表!$A:$B,2,FALSE),"")) -> 應付帳款 | G34: 2400
C35: 3-4月 | D35: 4100 | E35: =IF(D35="","",IFERROR(VLOOKUP(TEXT(D35,"0"),科目表!$A:$B,2,FALSE),"")) -> 銷貨收入 | F35: 217547 | G35: 217547
C36: 3-4月 | D36: 2134 | E36: =IF(D36="","",IFERROR(VLOOKUP(TEXT(D36,"0"),科目表!$A:$B,2,FALSE),"")) -> 銷項稅額 | F36: 10880 | G36: 10880
C37: 3-4月 | D37: 1123 | E37: =IF(D37="","",IFERROR(VLOOKUP(TEXT(D37,"0"),科目表!$A:$B,2,FALSE),"")) -> 應收帳款 | F37: 228427 | G37: 228427
C38: 3-4月 | D38: 1123 | E38: =IF(D38="","",IFERROR(VLOOKUP(TEXT(D38,"0"),科目表!$A:$B,2,FALSE),"")) -> 應收帳款
C39: 3-4月 | D39: 5100 | E39: =IF(D39="","",IFERROR(VLOOKUP(TEXT(D39,"0"),科目表!$A:$B,2,FALSE),"")) -> 銷貨成本 | F39: 122255
C40: 3-4月 | D40: 1144 | E40: =IF(D40="","",IFERROR(VLOOKUP(TEXT(D40,"0"),科目表!$A:$B,2,FALSE),"")) -> 進項稅額 | F40: 6113
C41: 3-4月 | D41: 2121 | E41: =IF(D41="","",IFERROR(VLOOKUP(TEXT(D41,"0"),科目表!$A:$B,2,FALSE),"")) -> 應付帳款 | G41: 128368
C42: 3-4月 | D42: 1144 | E42: =IF(D42="","",IFERROR(VLOOKUP(TEXT(D42,"0"),科目表!$A:$B,2,FALSE),"")) -> 進項稅額 | G42: 6113
C43: 3-4月 | D43: 2134 | E43: =IF(D43="","",IFERROR(VLOOKUP(TEXT(D43,"0"),科目表!$A:$B,2,FALSE),"")) -> 銷項稅額 | F43: 10880
C44: 3-4月 | D44: 2121 | E44: =IF(D44="","",IFERROR(VLOOKUP(TEXT(D44,"0"),科目表!$A:$B,2,FALSE),"")) -> 應付帳款 | G44: 4767
C45: 3-4月 | D45: 4100 | E45: =IF(D45="","",IFERROR(VLOOKUP(TEXT(D45,"0"),科目表!$A:$B,2,FALSE),"")) -> 銷貨收入 | G45: 217547
C46: 3-4月 | D46: 2134 | E46: =IF(D46="","",IFERROR(VLOOKUP(TEXT(D46,"0"),科目表!$A:$B,2,FALSE),"")) -> 銷項稅額 | G46: 10880
C47: 3-4月 | D47: 1123 | E47: =IF(D47="","",IFERROR(VLOOKUP(TEXT(D47,"0"),科目表!$A:$B,2,FALSE),"")) -> 應收帳款 | F47: 228427
C48: 5-6月 | D48: 4100 | E48: =IF(D48="","",IFERROR(VLOOKUP(TEXT(D48,"0"),科目表!$A:$B,2,FALSE),"")) -> 銷貨收入 | G48: 327831
C49: 5-6月 | D49: 2134 | E49: =IF(D49="","",IFERROR(VLOOKUP(TEXT(D49,"0"),科目表!$A:$B,2,FALSE),"")) -> 銷項稅額 | G49: 16390
C50: 5-6月 | D50: 1123 | E50: =IF(D50="","",IFERROR(VLOOKUP(TEXT(D50,"0"),科目表!$A:$B,2,FALSE),"")) -> 應收帳款 | F50: 344221
C51: 5-6月 | D51: 1123 | E51: =IF(D51="","",IFERROR(VLOOKUP(TEXT(D51,"0"),科目表!$A:$B,2,FALSE),"")) -> 應收帳款
C52: 5-6月 | D52: 5100 | E52: =IF(D52="","",IFERROR(VLOOKUP(TEXT(D52,"0"),科目表!$A:$B,2,FALSE),"")) -> 銷貨成本 | F52: 159296
C53: 5-6月 | D53: 1144 | E53: =IF(D53="","",IFERROR(VLOOKUP(TEXT(D53,"0"),科目表!$A:$B,2,FALSE),"")) -> 進項稅額 | F53: 7962
C54: 5-6月 | D54: 2121 | E54: =IF(D54="","",IFERROR(VLOOKUP(TEXT(D54,"0"),科目表!$A:$B,2,FALSE),"")) -> 應付帳款 | G54: 167258
C55: 5-6月 | D55: 1144 | E55: =IF(D55="","",IFERROR(VLOOKUP(TEXT(D55,"0"),科目表!$A:$B,2,FALSE),"")) -> 進項稅額 | G55: 7962
C56: 5-6月 | D56: 2134 | E56: =IF(D56="","",IFERROR(VLOOKUP(TEXT(D56,"0"),科目表!$A:$B,2,FALSE),"")) -> 銷項稅額 | F56: 16390
C57: 5-6月 | D57: 2121 | E57: =IF(D57="","",IFERROR(VLOOKUP(TEXT(D57,"0"),科目表!$A:$B,2,FALSE),"")) -> 應付帳款 | G57: 8428
C58: 7-8月 | D58: 4100 | E58: =IF(D58="","",IFERROR(VLOOKUP(TEXT(D58,"0"),科目表!$A:$B,2,FALSE),"")) -> 銷貨收入 | G58: 668783
C59: 7-8月 | D59: 2134 | E59: =IF(D59="","",IFERROR(VLOOKUP(TEXT(D59,"0"),科目表!$A:$B,2,FALSE),"")) -> 銷項稅額 | G59: 33439
C60: 7-8月 | D60: 1123 | E60: =IF(D60="","",IFERROR(VLOOKUP(TEXT(D60,"0"),科目表!$A:$B,2,FALSE),"")) -> 應收帳款 | F60: 702222
C61: 7-8月 | D61: 1123 | E61: =IF(D61="","",IFERROR(VLOOKUP(TEXT(D61,"0"),科目表!$A:$B,2,FALSE),"")) -> 應收帳款
C62: 7-8月 | D62: 5100 | E62: =IF(D62="","",IFERROR(VLOOKUP(TEXT(D62,"0"),科目表!$A:$B,2,FALSE),"")) -> 銷貨成本 | F62: 262627
C63: 7-8月 | D63: 1144 | E63: =IF(D63="","",IFERROR(VLOOKUP(TEXT(D63,"0"),科目表!$A:$B,2,FALSE),"")) -> 進項稅額 | F63: 13129
C64: 7-8月 | D64: 2121 | E64: =IF(D64="","",IFERROR(VLOOKUP(TEXT(D64,"0"),科目表!$A:$B,2,FALSE),"")) -> 應付帳款 | G64: 275756
C65: 7-8月 | D65: 1144 | E65: =IF(D65="","",IFERROR(VLOOKUP(TEXT(D65,"0"),科目表!$A:$B,2,FALSE),"")) -> 進項稅額 | G65: 13129
C66: 7-8月 | D66: 2134 | E66: =IF(D66="","",IFERROR(VLOOKUP(TEXT(D66,"0"),科目表!$A:$B,2,FALSE),"")) -> 銷項稅額 | F66: 33439
C67: 7-8月 | D67: 2121 | E67: =IF(D67="","",IFERROR(VLOOKUP(TEXT(D67,"0"),科目表!$A:$B,2,FALSE),"")) -> 應付帳款 | G67: 20310
C68: 9-10月 | D68: 4100 | E68: =IF(D68="","",IFERROR(VLOOKUP(TEXT(D68,"0"),科目表!$A:$B,2,FALSE),"")) -> 銷貨收入 | G68: 610107
C69: 9-10月 | D69: 2134 | E69: =IF(D69="","",IFERROR(VLOOKUP(TEXT(D69,"0"),科目表!$A:$B,2,FALSE),"")) -> 銷項稅額 | G69: 30509
C70: 9-10月 | D70: 1123 | E70: =IF(D70="","",IFERROR(VLOOKUP(TEXT(D70,"0"),科目表!$A:$B,2,FALSE),"")) -> 應收帳款 | F70: 640616
C71: 9-10月 | D71: 1461 | E71: =IF(D71="","",IFERROR(VLOOKUP(TEXT(D71,"0"),科目表!$A:$B,2,FALSE),"")) -> 生財器具 | F71: 44800
C72: 9-10月 | D72: 5100 | E72: =IF(D72="","",IFERROR(VLOOKUP(TEXT(D72,"0"),科目表!$A:$B,2,FALSE),"")) -> 銷貨成本 | F72: 267928
C73: 9-10月 | D73: 1144 | E73: =IF(D73="","",IFERROR(VLOOKUP(TEXT(D73,"0"),科目表!$A:$B,2,FALSE),"")) -> 進項稅額 | F73: 15628
C74: 9-10月 | D74: 2121 | E74: =IF(D74="","",IFERROR(VLOOKUP(TEXT(D74,"0"),科目表!$A:$B,2,FALSE),"")) -> 應付帳款 | G74: 328356
C75: 9-10月 | D75: 1144 | E75: =IF(D75="","",IFERROR(VLOOKUP(TEXT(D75,"0"),科目表!$A:$B,2,FALSE),"")) -> 進項稅額 | G75: 15628
C76: 9-10月 | D76: 2134 | E76: =IF(D76="","",IFERROR(VLOOKUP(TEXT(D76,"0"),科目表!$A:$B,2,FALSE),"")) -> 銷項稅額 | F76: 30509
C77: 9-10月 | D77: 2121 | E77: =IF(D77="","",IFERROR(VLOOKUP(TEXT(D77,"0"),科目表!$A:$B,2,FALSE),"")) -> 應付帳款 | G77: 14881
C78: 11-12月 | D78: 4100 | E78: =IF(D78="","",IFERROR(VLOOKUP(TEXT(D78,"0"),科目表!$A:$B,2,FALSE),"")) -> 銷貨收入 | G78: 501366
C79: 11-12月 | D79: 2134 | E79: =IF(D79="","",IFERROR(VLOOKUP(TEXT(D79,"0"),科目表!$A:$B,2,FALSE),"")) -> 銷項稅額 | G79: 25069
C80: 11-12月 | D80: 1123 | E80: =IF(D80="","",IFERROR(VLOOKUP(TEXT(D80,"0"),科目表!$A:$B,2,FALSE),"")) -> 應收帳款 | F80: 526435
C81: 11-12月 | D81: 1461 | E81: =IF(D81="","",IFERROR(VLOOKUP(TEXT(D81,"0"),科目表!$A:$B,2,FALSE),"")) -> 生財器具
C82: 11-12月 | D82: 5100 | E82: =IF(D82="","",IFERROR(VLOOKUP(TEXT(D82,"0"),科目表!$A:$B,2,FALSE),"")) -> 銷貨成本 | F82: 330270
C83: 11-12月 | D83: 1144 | E83: =IF(D83="","",IFERROR(VLOOKUP(TEXT(D83,"0"),科目表!$A:$B,2,FALSE),"")) -> 進項稅額 | F83: 16513
C84: 11-12月 | D84: 2121 | E84: =IF(D84="","",IFERROR(VLOOKUP(TEXT(D84,"0"),科目表!$A:$B,2,FALSE),"")) -> 應付帳款 | G84: 346783
C85: 1-12月 | D85: 6010 | E85: =IF(D85="","",IFERROR(VLOOKUP(TEXT(D85,"0"),科目表!$A:$B,2,FALSE),"")) -> 薪資支出 | F85: 528000
C86: 1-12月 | D86: 6010 | E86: =IF(D86="","",IFERROR(VLOOKUP(TEXT(D86,"0"),科目表!$A:$B,2,FALSE),"")) -> 薪資支出 | F86: 540000
C87: 薪資費用 | D87: 2121 | E87: =IF(D87="","",IFERROR(VLOOKUP(TEXT(D87,"0"),科目表!$A:$B,2,FALSE),"")) -> 應付帳款 | G87: 1068000
C88: 1-12月健保費用 | D88: 6100 | E88: =IF(D88="","",IFERROR(VLOOKUP(TEXT(D88,"0"),科目表!$A:$B,2,FALSE),"")) -> 保險費 | F88: 51360
C89: 1-12月健保費用 | D89: 2121 | E89: =IF(D89="","",IFERROR(VLOOKUP(TEXT(D89,"0"),科目表!$A:$B,2,FALSE),"")) -> 應付帳款 | G89: 51360
D90: 1123 | E90: =IF(D90="","",IFERROR(VLOOKUP(TEXT(D90,"0"),科目表!$A:$B,2,FALSE),"")) -> 應收帳款 | G90: 254360
D91: 2112 | E91: =IF(D91="","",IFERROR(VLOOKUP(TEXT(D91,"0"),科目表!$A:$B,2,FALSE),"")) -> 銀行借款 | F91: 254360
D92: 2121 | E92: =IF(D92="","",IFERROR(VLOOKUP(TEXT(D92,"0"),科目表!$A:$B,2,FALSE),"")) -> 應付帳款 | F92: 28062
D93: 11122 | E93: =IF(D93="","",IFERROR(VLOOKUP(TEXT(D93,"0"),科目表!$A:$B,2,FALSE),"")) -> 銀行存款-合庫 | G93: 28062
D94: 2121 | E94: =IF(D94="","",IFERROR(VLOOKUP(TEXT(D94,"0"),科目表!$A:$B,2,FALSE),"")) -> 應付帳款 | F94: 8782
D95: 11121 | E95: =IF(D95="","",IFERROR(VLOOKUP(TEXT(D95,"0"),科目表!$A:$B,2,FALSE),"")) -> 銀行存款-國泰 | G95: 8782
D96: 1123 | E96: =IF(D96="","",IFERROR(VLOOKUP(TEXT(D96,"0"),科目表!$A:$B,2,FALSE),"")) -> 應收帳款 | G96: 2200000
D97: 2121 | E97: =IF(D97="","",IFERROR(VLOOKUP(TEXT(D97,"0"),科目表!$A:$B,2,FALSE),"")) -> 應付帳款 | F97: 2200000
D98: 5100 | E98: =IF(D98="","",IFERROR(VLOOKUP(TEXT(D98,"0"),科目表!$A:$B,2,FALSE),"")) -> 銷貨成本 | G98: =25605+18950+3688+43500 -> 91743
D99: 6030 | E99: =IF(D99="","",IFERROR(VLOOKUP(TEXT(D99,"0"),科目表!$A:$B,2,FALSE),"")) -> 文具用品 | F99: 25605
D100: 6320 | E100: =IF(D100="","",IFERROR(VLOOKUP(TEXT(D100,"0"),科目表!$A:$B,2,FALSE),"")) -> 交通費 | F100: 18950
...

Sheet 資產負債表
A1: 資產負債表
A2: 截至 2025年12月31日 | B2: 泰瑞莎法迪有限公司
A4: 資產 | D4: 負債及權益
A5: 流動資產 | D5: 流動負債
A6: 1111 零用金 | B6: =IFERROR(VLOOKUP("1111",試算表!$A:$E,5,FALSE),0) -> 0 | D6: 2111 銀行透支 | E6: =IFERROR(VLOOKUP("2111",試算表!$A:$E,5,FALSE),0) -> 0
A7: 1112 銀行存款 | B7: =IFERROR(VLOOKUP("1112",試算表!$A:$E,5,FALSE),0) -> 0 | D7: 2112 銀行借款 | E7: =IFERROR(VLOOKUP("2112",試算表!$A:$E,5,FALSE),0) -> 171000
A8: 11121 銀行存款-國泰 | B8: =IFERROR(VLOOKUP("11121",試算表!$A:$E,5,FALSE),0) -> 11097 | D8: 2113 應付短期票券 | E8: =IFERROR(VLOOKUP("2113",試算表!$A:$E,5,FALSE),0) -> 0
A9: 11122 銀行存款-合庫 | B9: =IFERROR(VLOOKUP("11122",試算表!$A:$E,5,FALSE),0) -> 1773 | D9: 2119 其他短期借款 | E9: =IFERROR(VLOOKUP("2119",試算表!$A:$E,5,FALSE),0) -> 0
A10: 11123 銀行存款-台銀活存 | B10: =IFERROR(VLOOKUP("11123",試算表!$A:$E,5,FALSE),0) -> 0 | D10: 2140 透過損益按公允價值衡量之金融負債-流動 | E10: =IFERROR(VLOOKUP("2140",試算表!$A:$E,5,FALSE),0) -> 0
A11: 11124 銀行存款-台銀支存 | B11: =IFERROR(VLOOKUP("11124",試算表!$A:$E,5,FALSE),0) -> 0 | D11: 2150 避險之金融負債-流動 | E11: =IFERROR(VLOOKUP("2150",試算表!$A:$E,5,FALSE),0) -> 0
A12: 1113 約當現金 | B12: =IFERROR(VLOOKUP("1113",試算表!$A:$E,5,FALSE),0) -> 0 | D12: 2170 特別股負債-流動 | E12: =IFERROR(VLOOKUP("2170",試算表!$A:$E,5,FALSE),0) -> 0
A13: 1114 短期投資 | B13: =IFERROR(VLOOKUP("1114",試算表!$A:$E,5,FALSE),0) -> 0 | D13: 2180 其他金融負債-流動 | E13: =IFERROR(VLOOKUP("2180",試算表!$A:$E,5,FALSE),0) -> 0
A14: 1151 透過損益按公允價值衡量之金融資產-流動 | B14: =IFERROR(VLOOKUP("1151",試算表!$A:$E,5,FALSE),0) -> 0 | D14: 2126 合約負債-流動 | E14: =IFERROR(VLOOKUP("2126",試算表!$A:$E,5,FALSE),0) -> 0
A15: 1154 避險之金融資產-流動 | B15: =IFERROR(VLOOKUP("1154",試算表!$A:$E,5,FALSE),0) -> 0 | D15: 2120 應付票據 | E15: =IFERROR(VLOOKUP("2120",試算表!$A:$E,5,FALSE),0) -> 0
A16: 1158 透過其他綜合損益按公允價值衡量之金融資產-流動 | B16: =IFERROR(VLOOKUP("1158",試算表!$A:$E,5,FALSE),0) -> 0 | D16: 2121 應付帳款 | E16: =IFERROR(VLOOKUP("2121",試算表!$A:$E,5,FALSE),0) -> 1099111
A17: 1161 按攤銷後成本衡量之金融資產－流動 | B17: =IFERROR(VLOOKUP("1161",試算表!$A:$E,5,FALSE),0) -> 0 | D17: 2131 應付費用 | E17: =IFERROR(VLOOKUP("2131",試算表!$A:$E,5,FALSE),0) -> 0
A18: 1157 其他金融資產-流動 | B18: =IFERROR(VLOOKUP("1157",試算表!$A:$E,5,FALSE),0) -> 0 | D18: 2132 應付稅捐 | E18: =IFERROR(VLOOKUP("2132",試算表!$A:$E,5,FALSE),0) -> 0
A19: 1159 減:累計減損-金融資產-流動 | B19: =IFERROR(VLOOKUP("1159",試算表!$A:$E,5,FALSE),0) -> 0 | D19: 2133 應付股利 | E19: =IFERROR(VLOOKUP("2133",試算表!$A:$E,5,FALSE),0) -> 0
A20: 1125 合約資產-流動 | B20: =IFERROR(VLOOKUP("1125",試算表!$A:$E,5,FALSE),0) -> 0 | D20: 2134 銷項稅額 | E20: =IFERROR(VLOOKUP("2134",試算表!$A:$E,5,FALSE),0) -> 25069
A21: 1126 減:累計減損-合約資產-流動 | B21: =IFERROR(VLOOKUP("1126",試算表!$A:$E,5,FALSE),0) -> 0 | D21: 2135 其他應付款-其他 | E21: =IFERROR(VLOOKUP("2135",試算表!$A:$E,5,FALSE),0) -> 0
A22: 1121 應收票據 | B22: =IFERROR(VLOOKUP("1121",試算表!$A:$E,5,FALSE),0) -> 0 | D22: 2137 預收貨款 | E22: =IFERROR(VLOOKUP("2137",試算表!$A:$E,5,FALSE),0) -> 0
A23: 1122 減:備抵呆帳-應收票據 | B23: =IFERROR(VLOOKUP("1122",試算表!$A:$E,5,FALSE),0) -> 0 | D23: 2138 其他預收款 | E23: =IFERROR(VLOOKUP("2138",試算表!$A:$E,5,FALSE),0) -> 0
A24: 1123 應收帳款 | B24: =IFERROR(VLOOKUP("1123",試算表!$A:$E,5,FALSE),0) -> 159929 | D24: 2191 暫收款 | E24: =IFERROR(VLOOKUP("2191",試算表!$A:$E,5,FALSE),0) -> 0
A25: 1124 減:備抵呆帳-應收帳款 | B25: =IFERROR(VLOOKUP("1124",試算表!$A:$E,5,FALSE),0) -> 0 | D25: 2192 股東往來 | E25: =IFERROR(VLOOKUP("2192",試算表!$A:$E,5,FALSE),0) -> 0
A26: 1129 其他應收款 | B26: =IFERROR(VLOOKUP("1129",試算表!$A:$E,5,FALSE),0) -> 0 | D26: 2195 代收款 | E26: =IFERROR(VLOOKUP("2195",試算表!$A:$E,5,FALSE),0) -> 0
A27: 1131 商品 | B27: =IFERROR(VLOOKUP("1131",試算表!$A:$E,5,FALSE),0) -> 0 | D27: 21951 代收款-健保費 | E27: =IFERROR(VLOOKUP("21951",試算表!$A:$E,5,FALSE),0) -> 0
A28: 1132 製成品 | B28: =IFERROR(VLOOKUP("1132",試算表!$A:$E,5,FALSE),0) -> 0 | D28: 21952 代收款-勞保費 | E28: =IFERROR(VLOOKUP("21952",試算表!$A:$E,5,FALSE),0) -> 0
A29: 1133 在製品 | B29: =IFERROR(VLOOKUP("1133",試算表!$A:$E,5,FALSE),0) -> 0 | D29: 21953 代收款-扣繳稅款 | E29: =IFERROR(VLOOKUP("21953",試算表!$A:$E,5,FALSE),0) -> 0
A30: 1134 原料 | B30: =IFERROR(VLOOKUP("1134",試算表!$A:$E,5,FALSE),0) -> 0 | D30: 2196 其他流動負債-其他 | E30: =IFERROR(VLOOKUP("2196",試算表!$A:$E,5,FALSE),0) -> 0
A31: 1135 物料 | B31: =IFERROR(VLOOKUP("1135",試算表!$A:$E,5,FALSE),0) -> 0 | D31: 2210 應付公司債 | E31: =IFERROR(VLOOKUP("2210",試算表!$A:$E,5,FALSE),0) -> 0
A32: 1136 寄銷品 | B32: =IFERROR(VLOOKUP("1136",試算表!$A:$E,5,FALSE),0) -> 0 | D32: 2220 長期借款 | E32: =IFERROR(VLOOKUP("2220",試算表!$A:$E,5,FALSE),0) -> 0
A33: 1138 其他存貨 | B33: =IFERROR(VLOOKUP("1138",試算表!$A:$E,5,FALSE),0) -> 0 | D33: 2230 透過損益按公允價值衡量之金融負債-非流動 | E33: =IFERROR(VLOOKUP("2230",試算表!$A:$E,5,FALSE),0) -> 0
A34: 1137 備抵存貨跌價損失 | B34: =IFERROR(VLOOKUP("1137",試算表!$A:$E,5,FALSE),0) -> 0 | D34: 2240 避險之金融負債-非流動 | E34: =IFERROR(VLOOKUP("2240",試算表!$A:$E,5,FALSE),0) -> 0
A35: 1141 預付費用 | B35: =IFERROR(VLOOKUP("1141",試算表!$A:$E,5,FALSE),0) -> 0 | D35: 2260 特別股負債-非流動 | E35: =IFERROR(VLOOKUP("2260",試算表!$A:$E,5,FALSE),0) -> 0
A36: 1142 用品盤存 | B36: =IFERROR(VLOOKUP("1142",試算表!$A:$E,5,FALSE),0) -> 0 | D36: 2270 其他金融負債-非流動 | E36: =IFERROR(VLOOKUP("2270",試算表!$A:$E,5,FALSE),0) -> 0
A37: 1143 預付貨款 | B37: =IFERROR(VLOOKUP("1143",試算表!$A:$E,5,FALSE),0) -> 0 | D37: 2280 長期應付票據及款項 | E37: =IFERROR(VLOOKUP("2280",試算表!$A:$E,5,FALSE),0) -> 0
A38: 1144 進項稅額 | B38: =IFERROR(VLOOKUP("1144",試算表!$A:$E,5,FALSE),0) -> 16513 | D38: 2281 合約負債-非流動 | E38: =IFERROR(VLOOKUP("2281",試算表!$A:$E,5,FALSE),0) -> 0
A39: 1145 留抵稅額 | B39: =IFERROR(VLOOKUP("1145",試算表!$A:$E,5,FALSE),0) -> 0 | D39: 2290 其他長期負債 | E39: =IFERROR(VLOOKUP("2290",試算表!$A:$E,5,FALSE),0) -> 0
A40: 1149 其他預付款 | B40: =IFERROR(VLOOKUP("1149",試算表!$A:$E,5,FALSE),0) -> 0 | D40: 流動負債合計 | E40: =SUM(E6:E39) -> 1295180
A41: 1191 暫付款 | B41: =IFERROR(VLOOKUP("1191",試算表!$A:$E,5,FALSE),0) -> 0 | D41: 非流動負債
A42: 1192 股東往來 | B42: =IFERROR(VLOOKUP("1192",試算表!$A:$E,5,FALSE),0) -> 0 | D42: 2910 存入保證金 | E42: =IFERROR(VLOOKUP("2910",試算表!$A:$E,5,FALSE),0) -> 0
A43: 1193 同業往來 | B43: =IFERROR(VLOOKUP("1193",試算表!$A:$E,5,FALSE),0) -> 0 | D43: 2940 退休金準備 | E43: =IFERROR(VLOOKUP("2940",試算表!$A:$E,5,FALSE),0) -> 0
A44: 1199 其他流動資產-其他 | B44: =IFERROR(VLOOKUP("1199",試算表!$A:$E,5,FALSE),0) -> 0 | D44: 2951 國外投資損失準備 | E44: =IFERROR(VLOOKUP("2951",試算表!$A:$E,5,FALSE),0) -> 0
A45: 1300 長期性之投資 | B45: =IFERROR(VLOOKUP("1300",試算表!$A:$E,5,FALSE),0) -> 0 | D45: 2970 受託承銷品 | E45: =IFERROR(VLOOKUP("2970",試算表!$A:$E,5,FALSE),0) -> 0
A46: 流動資產合計 | B46: =SUM(B6:B45) -> 189312 | D46: 2999 其他非流動負債-其他 | E46: =IFERROR(VLOOKUP("2999",試算表!$A:$E,5,FALSE),0) -> 0
A47: 非流動資產 | D47: 非流動負債合計 | E47: =SUM(E42:E46) -> 0
A48: 1415 減:累計減損-長期性之投資 | B48: =IFERROR(VLOOKUP("1415",試算表!$A:$E,5,FALSE),0) -> 0 | D48: 股東權益
A49: 1612 透過損益按公允價值衡量之金融資產-非流動 | B49: =IFERROR(VLOOKUP("1612",試算表!$A:$E,5,FALSE),0) -> 0 | D49: 3110 實收資本 | E49: =IFERROR(VLOOKUP("3110",試算表!$A:$E,5,FALSE),0) -> 1000000
A50: 1615 避險之金融資產-非流動 | B50: =IFERROR(VLOOKUP("1615",試算表!$A:$E,5,FALSE),0) -> 0 | D50: 3330 資本公積 | E50: =IFERROR(VLOOKUP("3330",試算表!$A:$E,5,FALSE),0) -> 0
A51: 1621 透過其他綜合損益按公允價值衡量之金融資產-非流動 | B51: =IFERROR(VLOOKUP("1621",試算表!$A:$E,5,FALSE),0) -> 0 | D51: 3410 法定盈餘公積 | E51: =IFERROR(VLOOKUP("3410",試算表!$A:$E,5,FALSE),0) -> 0
A52: 1622 按攤銷後成本衡量之金融資產－非流動 | B52: =IFERROR(VLOOKUP("1622",試算表!$A:$E,5,FALSE),0) -> 0 | D52: 3420 特別盈餘公積 | E52: =IFERROR(VLOOKUP("3420",試算表!$A:$E,5,FALSE),0) -> 0
A53: 1618 其他金融資產-非流動 | B53: =IFERROR(VLOOKUP("1618",試算表!$A:$E,5,FALSE),0) -> 0 | D53: 3430 累積盈虧 | E53: =IFERROR(VLOOKUP("3430",試算表!$A:$E,5,FALSE),0) -> -1929131
A54: 1630 採用權益法之投資 | B54: =IFERROR(VLOOKUP("1630",試算表!$A:$E,5,FALSE),0) -> 0 | D54: 3434 追溯適用及追溯重編之影響數 | E54: =IFERROR(VLOOKUP("3434",試算表!$A:$E,5,FALSE),0) -> 0
A55: 1631 減:累計減損-金融資產-非流動 | B55: =IFERROR(VLOOKUP("1631",試算表!$A:$E,5,FALSE),0) -> 0 | D55: 3435 本年度其他綜合損益轉入之稅後淨額 | E55: =IFERROR(VLOOKUP("3435",試算表!$A:$E,5,FALSE),0) -> 0
A56: 1640 合約資產-非流動 | B56: =IFERROR(VLOOKUP("1640",試算表!$A:$E,5,FALSE),0) -> 0 | D56: 3440 本期損益 (結算科目，請勿複製) | E56: =損益表!B82 -> 111813
A57: 1641 減:累計減損-合約資產-非流動 | B57: =IFERROR(VLOOKUP("1641",試算表!$A:$E,5,FALSE),0) -> 0 | D57: 3502 避險中屬有效避險部分之避險工具損益 | E57: =IFERROR(VLOOKUP("3502",試算表!$A:$E,5,FALSE),0) -> 0
A58: 1410 土地 | B58: =IFERROR(VLOOKUP("1410",試算表!$A:$E,5,FALSE),0) -> 0 | D58: 3503 國外營運機構財務報表換算之兌換差額 | E58: =IFERROR(VLOOKUP("3503",試算表!$A:$E,5,FALSE),0) -> 0
A59: 1411 減:累計減損-土地 | B59: =IFERROR(VLOOKUP("1411",試算表!$A:$E,5,FALSE),0) -> 0 | D59: 3504 未實現重估增值 | E59: =IFERROR(VLOOKUP("3504",試算表!$A:$E,5,FALSE),0) -> 0
A60: 1431 房屋及建築 | B60: =IFERROR(VLOOKUP("1431",試算表!$A:$E,5,FALSE),0) -> 0 | D60: 3505 確定福利計畫再衡量數 | E60: =IFERROR(VLOOKUP("3505",試算表!$A:$E,5,FALSE),0) -> 0
A61: 1432 減:累計折舊-房屋及建築 | B61: =IFERROR(VLOOKUP("1432",試算表!$A:$E,5,FALSE),0) -> 0 | D61: 3507 透過其他綜合損益按公允價值衡量之未實現損益 | E61: =IFERROR(VLOOKUP("3507",試算表!$A:$E,5,FALSE),0) -> 0
A62: 1433 減:累計減損-房屋及建築 | B62: =IFERROR(VLOOKUP("1433",試算表!$A:$E,5,FALSE),0) -> 0 | D62: 3506 其他權益-其他 | E62: =IFERROR(VLOOKUP("3506",試算表!$A:$E,5,FALSE),0) -> 0
A63: 1441 機器設備 | B63: =IFERROR(VLOOKUP("1441",試算表!$A:$E,5,FALSE),0) -> 0 | D63: 3600 減:庫藏股票 | E63: =IFERROR(VLOOKUP("3600",試算表!$A:$E,5,FALSE),0) -> 0
A64: 1442 減:累計折舊-機器設備 | B64: =IFERROR(VLOOKUP("1442",試算表!$A:$E,5,FALSE),0) -> 0 | D64: 股東權益合計 | E64: =SUM(E49:E63) -> -817318
A65: 1443 減:累計減損-機器設備 | B65: =IFERROR(VLOOKUP("1443",試算表!$A:$E,5,FALSE),0) -> 0 | D65: 負債及權益總計 | E65: =E40+E47+E64 -> 477862
A66: 1451 運輸設備 | B66: =IFERROR(VLOOKUP("1451",試算表!$A:$E,5,FALSE),0) -> 0
A67: 驗證： | B67: =IF(B92=E65,"✓ 平衡","✗ 不平衡") -> ✓ 平衡
A68: 1453 減:累計減損-運輸設備 | B68: =IFERROR(VLOOKUP("1453",試算表!$A:$E,5,FALSE),0) -> 0
A69: 1461 生財器具 | B69: =IFERROR(VLOOKUP("1461",試算表!$A:$E,5,FALSE),0) -> 344800
A70: 1462 減:累計折舊-生財器具 | B70: =IFERROR(VLOOKUP("1462",試算表!$A:$E,5,FALSE),0) -> 106250
A71: 1463 減:累計減損-生財器具 | B71: =IFERROR(VLOOKUP("1463",試算表!$A:$E,5,FALSE),0) -> 0
A72: 1470 未完工程及待驗設備 | B72: =IFERROR(VLOOKUP("1470",試算表!$A:$E,5,FALSE),0) -> 0
A73: 1580 預付購置設備款 | B73: =IFERROR(VLOOKUP("1580",試算表!$A:$E,5,FALSE),0) -> 0
A74: 1491 其他固定資產 | B74: =IFERROR(VLOOKUP("1491",試算表!$A:$E,5,FALSE),0) -> 0
A75: 1492 減:累計折舊-其他固定資產 | B75: =IFERROR(VLOOKUP("1492",試算表!$A:$E,5,FALSE),0) -> 0 | H75: =B92-E65 -> 0
A76: 1493 減:累計減損-其他固定資產 | B76: =IFERROR(VLOOKUP("1493",試算表!$A:$E,5,FALSE),0) -> 0
A77: 1541 投資性不動產 | B77: =IFERROR(VLOOKUP("1541",試算表!$A:$E,5,FALSE),0) -> 0
A78: 1542 減:累計折舊-投資性不動產 | B78: =IFERROR(VLOOKUP("1542",試算表!$A:$E,5,FALSE),0) -> 0
A79: 1421 礦產資源 | B79: =IFERROR(VLOOKUP("1421",試算表!$A:$E,5,FALSE),0) -> 0
A80: 1422 減:累計折耗-礦產資源 | B80: =IFERROR(VLOOKUP("1422",試算表!$A:$E,5,FALSE),0) -> 0
A81: 1551 生物資產 | B81: =IFERROR(VLOOKUP("1551",試算表!$A:$E,5,FALSE),0) -> 0
A82: 1552 減:累計折舊-生物資產 | B82: =IFERROR(VLOOKUP("1552",試算表!$A:$E,5,FALSE),0) -> 0
A83: 1553 減:累計減損-生物資產 | B83: =IFERROR(VLOOKUP("1553",試算表!$A:$E,5,FALSE),0) -> 0
A84: 1510 無形資產 | B84: =IFERROR(VLOOKUP("1510",試算表!$A:$E,5,FALSE),0) -> 0
A85: 1511 減:累計攤折-無形資產 | B85: =IFERROR(VLOOKUP("1511",試算表!$A:$E,5,FALSE),0) -> 0
A86: 1512 減:累計減損-無形資產 | B86: =IFERROR(VLOOKUP("1512",試算表!$A:$E,5,FALSE),0) -> 0
A87: 1901 存出保證金 | B87: =IFERROR(VLOOKUP("1901",試算表!$A:$E,5,FALSE),0) -> 50000
A88: 1902 未攤銷費用 | B88: =IFERROR(VLOOKUP("1902",試算表!$A:$E,5,FALSE),0) -> 0
A89: 1903 預付設備款 | B89: =IFERROR(VLOOKUP("1903",試算表!$A:$E,5,FALSE),0) -> 0
A90: 1904 其他非流動資產-其他 | B90: =IFERROR(VLOOKUP("1904",試算表!$A:$E,5,FALSE),0) -> 0
A91: 非流動資產合計 | B91: =B69-B70+B87 -> 288550
A92: 資產總計 | B92: =B46+B91 -> 477862

Sheet 損益表
A1: 損益表
A2: 自 2025/1/172025/12/31 起 | B2: 泰瑞莎法迪有限公司
A4: 營業收入 | B4: =SUMIF(試算表!$F$2:$F$225,"收入",試算表!$E$2:$E$225) -> 2489793
A5: 4100 銷貨收入 | B5: =VLOOKUP("4100",試算表!$A:$E,5,FALSE) -> 2489793
A6: 4110 減:銷貨退回 | B6: =VLOOKUP("4110",試算表!$A:$E,5,FALSE) -> 0
A7: 4120 減:銷貨折讓 | B7: =VLOOKUP("4120",試算表!$A:$E,5,FALSE) -> 0
A8: 4200 勞務收入 | B8: =VLOOKUP("4200",試算表!$A:$E,5,FALSE) -> 0
A9: 4300 加工收入 | B9: =VLOOKUP("4300",試算表!$A:$E,5,FALSE) -> 0
A10: 4400 工程收入 | B10: =VLOOKUP("4400",試算表!$A:$E,5,FALSE) -> 0
A12: 銷貨成本 | B12: =SUMIF(試算表!$F$2:$F$225,"銷貨成本",試算表!$E$2:$E$225) -> 1166877
A13: 5100 銷貨成本 | B13: =VLOOKUP("5100",試算表!$A:$E,5,FALSE) -> 1166877
A14: 5200 勞務成本 | B14: =VLOOKUP("5200",試算表!$A:$E,5,FALSE) -> 0
A15: 5300 加工成本 | B15: =VLOOKUP("5300",試算表!$A:$E,5,FALSE) -> 0
A16: 5400 工程成本 | B16: =VLOOKUP("5400",試算表!$A:$E,5,FALSE) -> 0
A18: 營業毛利 | B18: =B4-B12 -> 1322916
A20: 營業費用 | B20: =SUMIF(試算表!$F$2:$F$225,"費用",試算表!$E$2:$E$225) -> 1211103
A21: 6010 薪資支出 | B21: =VLOOKUP("6010",試算表!$A:$E,5,FALSE) -> 1068000
A22: 6020 租金支出 | B22: =VLOOKUP("6020",試算表!$A:$E,5,FALSE) -> 0
A23: 6030 文具用品 | B23: =VLOOKUP("6030",試算表!$A:$E,5,FALSE) -> 25605
A24: 6040 旅費 | B24: =VLOOKUP("6040",試算表!$A:$E,5,FALSE) -> 0
A25: 6050 運費 | B25: =VLOOKUP("6050",試算表!$A:$E,5,FALSE) -> 0
A26: 6060 郵電費 | B26: =VLOOKUP("6060",試算表!$A:$E,5,FALSE) -> 0
A27: 6070 修繕費 | B27: =VLOOKUP("6070",試算表!$A:$E,5,FALSE) -> 0
A28: 6080 廣告費 | B28: =VLOOKUP("6080",試算表!$A:$E,5,FALSE) -> 0
A29: 6090 水電瓦斯費 | B29: =VLOOKUP("6090",試算表!$A:$E,5,FALSE) -> 43500
A30: 6100 保險費 | B30: =VLOOKUP("6100",試算表!$A:$E,5,FALSE) -> 51360
A31: 6110 交際費 | B31: =VLOOKUP("6110",試算表!$A:$E,5,FALSE) -> 0
A32: 6120 捐贈 | B32: =VLOOKUP("6120",試算表!$A:$E,5,FALSE) -> 0
A33: 6130 稅捐 | B33: =VLOOKUP("6130",試算表!$A:$E,5,FALSE) -> 0
A34: 6140 呆帳損失 | B34: =VLOOKUP("6140",試算表!$A:$E,5,FALSE) -> 0
A35: 6150 折舊 | B35: =VLOOKUP("6150",試算表!$A:$E,5,FALSE) -> 0
A36: 6160 各項耗竭及攤提 | B36: =VLOOKUP("6160",試算表!$A:$E,5,FALSE) -> 0
A37: 6170 外銷損失 | B37: =VLOOKUP("6170",試算表!$A:$E,5,FALSE) -> 0
A38: 6180 伙食費 | B38: =VLOOKUP("6180",試算表!$A:$E,5,FALSE) -> 0
A39: 6190 職工福利 | B39: =VLOOKUP("6190",試算表!$A:$E,5,FALSE) -> 0
A40: 6200 研究費 | B40: =VLOOKUP("6200",試算表!$A:$E,5,FALSE) -> 0
A41: 6210 佣金支出 | B41: =VLOOKUP("6210",試算表!$A:$E,5,FALSE) -> 0
A42: 6220 訓練費 | B42: =VLOOKUP("6220",試算表!$A:$E,5,FALSE) -> 0
A43: 6230 其他費用 | B43: =VLOOKUP("6230",試算表!$A:$E,5,FALSE) -> 0
A44: 6240 加班費 | B44: =VLOOKUP("6240",試算表!$A:$E,5,FALSE) -> 0
A45: 6250 退休金 | B45: =VLOOKUP("6250",試算表!$A:$E,5,FALSE) -> 0
A46: 6260 書報雜誌 | B46: =VLOOKUP("6260",試算表!$A:$E,5,FALSE) -> 0
A47: 6270 雜項購置 | B47: =VLOOKUP("6270",試算表!$A:$E,5,FALSE) -> 0
A48: 6280 出口費用 | B48: =VLOOKUP("6280",試算表!$A:$E,5,FALSE) -> 0
A49: 6290 手續費 | B49: =VLOOKUP("6290",試算表!$A:$E,5,FALSE) -> 3688
A50: 6300 匯費 | B50: =VLOOKUP("6300",試算表!$A:$E,5,FALSE) -> 0
A51: 6310 檢驗費 | B51: =VLOOKUP("6310",試算表!$A:$E,5,FALSE) -> 0
A52: 6320 交通費 | B52: =VLOOKUP("6320",試算表!$A:$E,5,FALSE) -> 18950
A53: 6330 公會費 | B53: =VLOOKUP("6330",試算表!$A:$E,5,FALSE) -> 0
A54: 6340 燃料費 | B54: =VLOOKUP("6340",試算表!$A:$E,5,FALSE) -> 0
A55: 6350 醫藥費 | B55: =VLOOKUP("6350",試算表!$A:$E,5,FALSE) -> 0
A56: 6360 規費 | B56: =VLOOKUP("6360",試算表!$A:$E,5,FALSE) -> 0
A57: 6370 包裝費 | B57: =VLOOKUP("6370",試算表!$A:$E,5,FALSE) -> 0
A58: 6380 加工費用 | B58: =VLOOKUP("6380",試算表!$A:$E,5,FALSE) -> 0
A59: 6390 消耗費 | B59: =VLOOKUP("6390",試算表!$A:$E,5,FALSE) -> 0
A60: 6400 勞務費 | B60: =VLOOKUP("6400",試算表!$A:$E,5,FALSE) -> 0
A61: 6410 倉租 | B61: =VLOOKUP("6410",試算表!$A:$E,5,FALSE) -> 0
A62: 6420 報關費 | B62: =VLOOKUP("6420",試算表!$A:$E,5,FALSE) -> 0
A63: 6430 進口運費 | B63: =VLOOKUP("6430",試算表!$A:$E,5,FALSE) -> 0
A64: 6440 出口結匯費 | B64: =VLOOKUP("6440",試算表!$A:$E,5,FALSE) -> 0
A65: 6450 碼頭工資 | B65: =VLOOKUP("6450",試算表!$A:$E,5,FALSE) -> 0
A66: 6460 服務費 | B66: =VLOOKUP("6460",試算表!$A:$E,5,FALSE) -> 0
A67: 6470 清潔費 | B67: =VLOOKUP("6470",試算表!$A:$E,5,FALSE) -> 0
A68: 6480 樣品費 | B68: =VLOOKUP("6480",試算表!$A:$E,5,FALSE) -> 0
A69: 6490 稿費 | B69: =VLOOKUP("6490",試算表!$A:$E,5,FALSE) -> 0
A70: 6500 排印費 | B70: =VLOOKUP("6500",試算表!$A:$E,5,FALSE) -> 0
A71: 6510 製版費 | B71: =VLOOKUP("6510",試算表!$A:$E,5,FALSE) -> 0
A72: 6520 出版費 | B72: =VLOOKUP("6520",試算表!$A:$E,5,FALSE) -> 0
A73: 6530 工具費 | B73: =VLOOKUP("6530",試算表!$A:$E,5,FALSE) -> 0
A75: 營業淨利 | B75: =B18-B20 -> 111813
A77: 稅前損益 | B77: =B75 -> 111813
A78: 所得稅費用 | B78: =SUMIF(試算表!$F$2:$F$225,"所得稅",試算表!$E$2:$E$225) -> 0
A79: 9000 所得稅費用(利益) | B79: =VLOOKUP("9000",試算表!$A:$E,5,FALSE) -> 0
A80: 9500 本期其他綜合損益(稅後淨額) | B80: =VLOOKUP("9500",試算表!$A:$E,5,FALSE) -> 0
A82: 稅後損益 | B82: =B77-B78 -> 111813

Sheet VAT計算
A1: 增值稅（VAT）計算
A2: 台灣營業稅率：5%
A4: 進項稅額（科目 1144） | B4: =VLOOKUP("1144",試算表!$A:$E,5,FALSE) -> 16513
A6: 銷項稅額（科目 2134） | B6: =SUMIF(試算表!A:A,"2134",試算表!E:E) -> 25069
A8: 應繳增值稅 | B8: =B6-B4 -> 8556
A11: 說明：
A12: 應繳 VAT > 0：需繳稅
A13: 應繳 VAT < 0：可退稅（負數表示待退）
A14: 應繳 VAT = 0：不需繳退
